Workbook
Name _xlcn.WorksheetConnection_Pivot_Store_DimA1B51: #REF!
Name _xlcn.WorksheetConnection_Customer_DimL1M5011: Customer_Dim!$L$1:$M$501

Sheet Customer_Dim
A1: Customer_ID | B1: Name | C1: Age | D1: Gender | E1: City | F1: State | G1: COUNTRY | H1: Loyalty_Level | I1: Clean_Name | J1: Clean_City | K1: Clean_State | L1: Clean_Gender | M1: Loyalty_Filled | N1: Age_Check
A2: CUST1000 | B2: sheena bonilla | C2: 55 | D2: Male | E2: Donaldton | F2: North Carolina | G2: USA | I2: =PROPER(B2) -> Sheena Bonilla | J2: =TRIM(PROPER(E2)) -> Donaldton | K2: =TRIM(PROPER(F2)) -> North Carolina | L2: =TRIM(PROPER(D2)) -> Male | M2: =IF(H2="","Standard",H2) -> Standard | N2: =IF(OR(C2<18,C2>70),"Check","OK") -> OK
A3: CUST1001 | B3: Eugene Nelson | C3: 26 | D3: Female | E3: Phillipsmouth | F3: North Dakota | G3: USA | H3: Platinum | I3: =PROPER(B3) -> Eugene Nelson | J3: =TRIM(PROPER(E3)) -> Phillipsmouth | K3: =TRIM(PROPER(F3)) -> North Dakota | L3: =TRIM(PROPER(D3)) -> Female | M3: =IF(H3="","Standard",H3) -> Platinum | N3: =IF(OR(C3<18,C3>70),"Check","OK") -> OK
A4: CUST1002 | B4: dr. Benjamin Price | C4: 29 | D4: Female | E4: Kylebury | F4: Alabama | G4: USA | H4: Platinum | I4: =PROPER(B4) -> Dr. Benjamin Price | J4: =TRIM(PROPER(E4)) -> Kylebury | K4: =TRIM(PROPER(F4)) -> Alabama | L4: =TRIM(PROPER(D4)) -> Female | M4: =IF(H4="","Standard",H4) -> Platinum | N4: =IF(OR(C4<18,C4>70),"Check","OK") -> OK
A5: CUST1003 | B5: jeremy harris | C5: 59 | D5: Female | E5: Thomastown | F5: Ohio | G5: USA | H5: Bronze | I5: =PROPER(B5) -> Jeremy Harris | J5: =TRIM(PROPER(E5)) -> Thomastown | K5: =TRIM(PROPER(F5)) -> Ohio | L5: =TRIM(PROPER(D5)) -> Female | M5: =IF(H5="","Standard",H5) -> Bronze | N5: =IF(OR(C5<18,C5>70),"Check","OK") -> OK
A6: CUST1004 | B6: Caroline Collins | C6: 64 | D6: Female | E6: Nicholasshire | F6: California | G6: USA | H6: Silver | I6: =PROPER(B6) -> Caroline Collins | J6: =TRIM(PROPER(E6)) -> Nicholasshire | K6: =TRIM(PROPER(F6)) -> California | L6: =TRIM(PROPER(D6)) -> Female | M6: =IF(H6="","Standard",H6) -> Silver | N6: =IF(OR(C6<18,C6>70),"Check","OK") -> OK
A7: CUST1005 | B7: Christine Vaughn | C7: 24 | D7: Male | E7: East Amandamouth | F7: Oregon | G7: USA | H7: Bronze | I7: =PROPER(B7) -> Christine Vaughn | J7: =TRIM(PROPER(E7)) -> East Amandamouth | K7: =TRIM(PROPER(F7)) -> Oregon | L7: =TRIM(PROPER(D7)) -> Male | M7: =IF(H7="","Standard",H7) -> Bronze | N7: =IF(OR(C7<18,C7>70),"Check","OK") -> OK
A8: CUST1006 | B8: Amber Jackson | C8: 29 | D8: Female | E8: Deborahborough | F8: South Dakota | G8: USA | H8: Platinum | I8: =PROPER(B8) -> Amber Jackson | J8: =TRIM(PROPER(E8)) -> Deborahborough | K8: =TRIM(PROPER(F8)) -> South Dakota | L8: =TRIM(PROPER(D8)) -> Female | M8: =IF(H8="","Standard",H8) -> Platinum | N8: =IF(OR(C8<18,C8>70),"Check","OK") -> OK
A9: CUST1007 | B9: Daniel Boyd | C9: 29 | D9: Female | E9: West Pamelafurt | F9: West Virginia | G9: USA | H9: Bronze | I9: =PROPER(B9) -> Daniel Boyd | J9: =TRIM(PROPER(E9)) -> West Pamelafurt | K9: =TRIM(PROPER(F9)) -> West Virginia | L9: =TRIM(PROPER(D9)) -> Female | M9: =IF(H9="","Standard",H9) -> Bronze | N9: =IF(OR(C9<18,C9>70),"Check","OK") -> OK
A10: CUST1008 | B10: Melissa Howard | C10: 53 | D10: Female | E10: Maynardton | F10: New Hampshire | G10: USA | H10: Gold | I10: =PROPER(B10) -> Melissa Howard | J10: =TRIM(PROPER(E10)) -> Maynardton | K10: =TRIM(PROPER(F10)) -> New Hampshire | L10: =TRIM(PROPER(D10)) -> Female | M10: =IF(H10="","Standard",H10) -> Gold | N10: =IF(OR(C10<18,C10>70),"Check","OK") -> OK
A11: CUST1009 | B11: Ms. Maria Leach | C11: 64 | D11: Male | E11: Melissashire | F11: Pennsylvania | G11: USA | H11: Platinum | I11: =PROPER(B11) -> Ms. Maria Leach | J11: =TRIM(PROPER(E11)) -> Melissashire | K11: =TRIM(PROPER(F11)) -> Pennsylvania | L11: =TRIM(PROPER(D11)) -> Male | M11: =IF(H11="","Standard",H11) -> Platinum | N11: =IF(OR(C11<18,C11>70),"Check","OK") -> OK
A12: CUST1010 | B12: Dominic Page | C12: 53 | D12: Male | E12: Port Michaelburgh | F12: Pennsylvania | G12: USA | H12: Bronze | I12: =PROPER(B12) -> Dominic Page | J12: =TRIM(PROPER(E12)) -> Port Michaelburgh | K12: =TRIM(PROPER(F12)) -> Pennsylvania | L12: =TRIM(PROPER(D12)) -> Male | M12: =IF(H12="","Standard",H12) -> Bronze | N12: =IF(OR(C12<18,C12>70),"Check","OK") -> OK
A13: CUST1011 | B13: Brian Lopez | C13: 28 | D13: Female | E13: East Krista | F13: New York | G13: USA | H13: Gold | I13: =PROPER(B13) -> Brian Lopez | J13: =TRIM(PROPER(E13)) -> East Krista | K13: =TRIM(PROPER(F13)) -> New York | L13: =TRIM(PROPER(D13)) -> Female | M13: =IF(H13="","Standard",H13) -> Gold | N13: =IF(OR(C13<18,C13>70),"Check","OK") -> OK
A14: CUST1012 | B14: Kenneth Lambert | C14: 55 | D14: Female | E14: North Kathryn | F14: Kansas | G14: USA | H14: Platinum | I14: =PROPER(B14) -> Kenneth Lambert | J14: =TRIM(PROPER(E14)) -> North Kathryn | K14: =TRIM(PROPER(F14)) -> Kansas | L14: =TRIM(PROPER(D14)) -> Female | M14: =IF(H14="","Standard",H14) -> Platinum | N14: =IF(OR(C14<18,C14>70),"Check","OK") -> OK
... A19: CUST1017 | B19: Adam Cruz | C19: 60 | D19: Female | E19: Brandonville | F19: Georgia | G19: USA | H19: Platinum | I19: =PROPER(B19) -> Adam Cruz | J19: =TRIM(PROPER(E19)) -> Brandonville | K19: =TRIM(PROPER(F19)) -> Georgia | L19: =TRIM(PROPER(D19)) -> Female | M19: =IF(H19="","Standard",H19) -> Platinum | N19: =IF(OR(C19<18,C19>70),"Check","OK") -> OK
A20: CUST1018 | B20: Rhonda Moss | C20: 43 | D20: Male | E20: South William | F20: Kansas | G20: USA | I20: =PROPER(B20) -> Rhonda Moss | J20: =TRIM(PROPER(E20)) -> South William | K20: =TRIM(PROPER(F20)) -> Kansas | L20: =TRIM(PROPER(D20)) -> Male | M20: =IF(H20="","Standard",H20) -> Standard | N20: =IF(OR(C20<18,C20>70),"Check","OK") -> OK
A21: CUST1019 | B21: Michael Torres | C21: 46 | D21: Female | E21: Gonzalezfort | F21: New Jersey | G21: USA | H21: Platinum | I21: =PROPER(B21) -> Michael Torres | J21: =TRIM(PROPER(E21)) -> Gonzalezfort | K21: =TRIM(PROPER(F21)) -> New Jersey | L21: =TRIM(PROPER(D21)) -> Female | M21: =IF(H21="","Standard",H21) -> Platinum | N21: =IF(OR(C21<18,C21>70),"Check","OK") -> OK
A22: CUST1020 | B22: Bridget Allen | C22: 59 | D22: Male | E22: Lake Shaneburgh | F22: Delaware | G22: USA | H22: Silver | I22: =PROPER(B22) -> Bridget Allen | J22: =TRIM(PROPER(E22)) -> Lake Shaneburgh | K22: =TRIM(PROPER(F22)) -> Delaware | L22: =TRIM(PROPER(D22)) -> Male | M22: =IF(H22="","Standard",H22) -> Silver | N22: =IF(OR(C22<18,C22>70),"Check","OK") -> OK
A23: CUST1021 | B23: Jeff Martinez | C23: 36 | D23: Female | E23: Smithburgh | F23: Oklahoma | G23: USA | H23: Gold | I23: =PROPER(B23) -> Jeff Martinez | J23: =TRIM(PROPER(E23)) -> Smithburgh | K23: =TRIM(PROPER(F23)) -> Oklahoma | L23: =TRIM(PROPER(D23)) -> Female | M23: =IF(H23="","Standard",H23) -> Gold | N23: =IF(OR(C23<18,C23>70),"Check","OK") -> OK
A24: CUST1022 | B24: paul fox | C24: 33 | D24: Female | E24: Michaelton | F24: Hawaii | G24: USA | H24: Silver | I24: =PROPER(B24) -> Paul Fox | J24: =TRIM(PROPER(E24)) -> Michaelton | K24: =TRIM(PROPER(F24)) -> Hawaii | L24: =TRIM(PROPER(D24)) -> Female | M24: =IF(H24="","Standard",H24) -> Silver | N24: =IF(OR(C24<18,C24>70),"Check","OK") -> OK
A25: CUST1023 | B25: Jonathan Steele | C25: 52 | D25: Female | E25: Molinabury | F25: Oregon | G25: USA | H25: Silver | I25: =PROPER(B25) -> Jonathan Steele | J25: =TRIM(PROPER(E25)) -> Molinabury | K25: =TRIM(PROPER(F25)) -> Oregon | L25: =TRIM(PROPER(D25)) -> Female | M25: =IF(H25="","Standard",H25) -> Silver | N25: =IF(OR(C25<18,C25>70),"Check","OK") -> OK
A26: CUST1024 | B26: Heather Collins | C26: 40 | D26: Male | E26: Rogerschester | F26: Idaho | G26: USA | H26: Platinum | I26: =PROPER(B26) -> Heather Collins | J26: =TRIM(PROPER(E26)) -> Rogerschester | K26: =TRIM(PROPER(F26)) -> Idaho | L26: =TRIM(PROPER(D26)) -> Male | M26: =IF(H26="","Standard",H26) -> Platinum | N26: =IF(OR(C26<18,C26>70),"Check","OK") -> OK
A27: CUST1025 | B27: Diana Taylor | C27: 59 | D27: Female | E27: Vasqueztown | F27: California | G27: USA | H27: Bronze | I27: =PROPER(B27) -> Diana Taylor | J27: =TRIM(PROPER(E27)) -> Vasqueztown | K27: =TRIM(PROPER(F27)) -> California | L27: =TRIM(PROPER(D27)) -> Female | M27: =IF(H27="","Standard",H27) -> Bronze | N27: =IF(OR(C27<18,C27>70),"Check","OK") -> OK
A28: CUST1026 | B28: Amber Carlson | C28: 18 | D28: Female | E28: East Michellemouth | F28: Missouri | G28: USA | H28: Gold | I28: =PROPER(B28) -> Amber Carlson | J28: =TRIM(PROPER(E28)) -> East Michellemouth | K28: =TRIM(PROPER(F28)) -> Missouri | L28: =TRIM(PROPER(D28)) -> Female | M28: =IF(H28="","Standard",H28) -> Gold | N28: =IF(OR(C28<18,C28>70),"Check","OK") -> OK
A29: CUST1027 | B29: Leslie Johnson | C29: 31 | D29: Male | E29: Mollyshire | F29: Utah | G29: USA | I29: =PROPER(B29) -> Leslie Johnson | J29: =TRIM(PROPER(E29)) -> Mollyshire | K29: =TRIM(PROPER(F29)) -> Utah | L29: =TRIM(PROPER(D29)) -> Male | M29: =IF(H29="","Standard",H29) -> Standard | N29: =IF(OR(C29<18,C29>70),"Check","OK") -> OK
A30: CUST1028 | B30: Joshua Ryan | C30: 27 | D30: Female | E30: New David | F30: New Jersey | G30: USA | H30: Platinum | I30: =PROPER(B30) -> Joshua Ryan | J30: =TRIM(PROPER(E30)) -> New David | K30: =TRIM(PROPER(F30)) -> New Jersey | L30: =TRIM(PROPER(D30)) -> Female | M30: =IF(H30="","Standard",H30) -> Platinum | N30: =IF(OR(C30<18,C30>70),"Check","OK") -> OK
A31: CUST1029 | B31: David Arnold | C31: 54 | D31: Female | E31: East Jennifer | F31: California | G31: USA | H31: Silver | I31: =PROPER(B31) -> David Arnold | J31: =TRIM(PROPER(E31)) -> East Jennifer | K31: =TRIM(PROPER(F31)) -> California | L31: =TRIM(PROPER(D31)) -> Female | M31: =IF(H31="","Standard",H31) -> Silver | N31: =IF(OR(C31<18,C31>70),"Check","OK") -> OK
A32: CUST1030 | B32: Jessica Acevedo | C32: 64 | D32: Female | E32: Amybury | F32: Pennsylvania | G32: USA | H32: Bronze | I32: =PROPER(B32) -> Jessica Acevedo | J32: =TRIM(PROPER(E32)) -> Amybury | K32: =TRIM(PROPER(F32)) -> Pennsylvania | L32: =TRIM(PROPER(D32)) -> Female | M32: =IF(H32="","Standard",H32) -> Bronze | N32: =IF(OR(C32<18,C32>70),"Check","OK") -> OK
A33: CUST1031 | B33: Sarah Vance | C33: 41 | D33: Male | E33: Johnsonville | F33: Oregon | G33: USA | H33: Silver | I33: =PROPER(B33) -> Sarah Vance | J33: =TRIM(PROPER(E33)) -> Johnsonville | K33: =TRIM(PROPER(F33)) -> Oregon | L33: =TRIM(PROPER(D33)) -> Male | M33: =IF(H33="","Standard",H33) -> Silver | N33: =IF(OR(C33<18,C33>70),"Check","OK") -> OK
A34: CUST1032 | B34: Mike Jennings | C34: 48 | D34: Female | E34: Fostermouth | F34: Arizona | G34: USA | H34: Gold | I34: =PROPER(B34) -> Mike Jennings | J34: =TRIM(PROPER(E34)) -> Fostermouth | K34: =TRIM(PROPER(F34)) -> Arizona | L34: =TRIM(PROPER(D34)) -> Female | M34: =IF(H34="","Standard",H34) -> Gold | N34: =IF(OR(C34<18,C34>70),"Check","OK") -> OK
A35: CUST1033 | B35: Robert Jones DDS | C35: 25 | D35: Male | E35: Tristanton | F35: Oklahoma | G35: USA | H35: Platinum | I35: =PROPER(B35) -> Robert Jones Dds | J35: =TRIM(PROPER(E35)) -> Tristanton | K35: =TRIM(PROPER(F35)) -> Oklahoma | L35: =TRIM(PROPER(D35)) -> Male | M35: =IF(H35="","Standard",H35) -> Platinum | N35: =IF(OR(C35<18,C35>70),"Check","OK") -> OK
A36: CUST1034 | B36: Christopher Olson | C36: 27 | D36: Female | E36: West Richard | F36: Maryland | G36: USA | H36: Platinum | I36: =PROPER(B36) -> Christopher Olson | J36: =TRIM(PROPER(E36)) -> West Richard | K36: =TRIM(PROPER(F36)) -> Maryland | L36: =TRIM(PROPER(D36)) -> Female | M36: =IF(H36="","Standard",H36) -> Platinum | N36: =IF(OR(C36<18,C36>70),"Check","OK") -> OK
A37: CUST1035 | B37: Rachel Myers | C37: 52 | D37: Male | E37: Robertberg | F37: North Dakota | G37: USA | H37: Silver | I37: =PROPER(B37) -> Rachel Myers | J37: =TRIM(PROPER(E37)) -> Robertberg | K37: =TRIM(PROPER(F37)) -> North Dakota | L37: =TRIM(PROPER(D37)) -> Male | M37: =IF(H37="","Standard",H37) -> Silver | N37: =IF(OR(C37<18,C37>70),"Check","OK") -> OK
A38: CUST1036 | B38: Thomas Phillips | C38: 20 | D38: Female | E38: Luisfurt | F38: Georgia | G38: USA | H38: Gold | I38: =PROPER(B38) -> Thomas Phillips | J38: =TRIM(PROPER(E38)) -> Luisfurt | K38: =TRIM(PROPER(F38)) -> Georgia | L38: =TRIM(PROPER(D38)) -> Female | M38: =IF(H38="","Standard",H38) -> Gold | N38: =IF(OR(C38<18,C38>70),"Check","OK") -> OK
A39: CUST1037 | B39: Christopher Carter | C39: 27 | D39: Female | E39: Brendastad | F39: South Dakota | G39: USA | I39: =PROPER(B39) -> Christopher Carter | J39: =TRIM(PROPER(E39)) -> Brendastad | K39: =TRIM(PROPER(F39)) -> South Dakota | L39: =TRIM(PROPER(D39)) -> Female | M39: =IF(H39="","Standard",H39) -> Standard | N39: =IF(OR(C39<18,C39>70),"Check","OK") -> OK
A40: CUST1038 | B40: Deanna Simpson | C40: 35 | D40: Female | E40: Brownport | F40: North Dakota | G40: USA | H40: Bronze | I40: =PROPER(B40) -> Deanna Simpson | J40: =TRIM(PROPER(E40)) -> Brownport | K40: =TRIM(PROPER(F40)) -> North Dakota | L40: =TRIM(PROPER(D40)) -> Female | M40: =IF(H40="","Standard",H40) -> Bronze | N40: =IF(OR(C40<18,C40>70),"Check","OK") -> OK
A41: CUST1039 | B41: Tonya Reynolds | C41: 55 | D41: Female | E41: Darleneton | F41: Michigan | G41: USA | H41: Gold | I41: =PROPER(B41) -> Tonya Reynolds | J41: =TRIM(PROPER(E41)) -> Darleneton | K41: =TRIM(PROPER(F41)) -> Michigan | L41: =TRIM(PROPER(D41)) -> Female | M41: =IF(H41="","Standard",H41) -> Gold | N41: =IF(OR(C41<18,C41>70),"Check","OK") -> OK
A42: CUST1040 | B42: Eric Vega | C42: 50 | D42: Male | E42: Williamsonland | F42: Kansas | G42: USA | H42: Gold | I42: =PROPER(B42) -> Eric Vega | J42: =TRIM(PROPER(E42)) -> Williamsonland | K42: =TRIM(PROPER(F42)) -> Kansas | L42: =TRIM(PROPER(D42)) -> Male | M42: =IF(H42="","Standard",H42) -> Gold | N42: =IF(OR(C42<18,C42>70),"Check","OK") -> OK
A43: CUST1041 | B43: James Gibbs | C43: 21 | D43: Male | E43: Mooneyshire | F43: Alaska | G43: USA | H43: Platinum | I43: =PROPER(B43) -> James Gibbs | J43: =TRIM(PROPER(E43)) -> Mooneyshire | K43: =TRIM(PROPER(F43)) -> Alaska | L43: =TRIM(PROPER(D43)) -> Male | M43: =IF(H43="","Standard",H43) -> Platinum | N43: =IF(OR(C43<18,C43>70),"Check","OK") -> OK
A44: CUST1042 | B44: William Martin | C44: 19 | D44: Male | E44: Ryanburgh | F44: Connecticut | G44: USA | H44: Platinum | I44: =PROPER(B44) -> William Martin | J44: =TRIM(PROPER(E44)) -> Ryanburgh | K44: =TRIM(PROPER(F44)) -> Connecticut | L44: =TRIM(PROPER(D44)) -> Male | M44: =IF(H44="","Standard",H44) -> Platinum | N44: =IF(OR(C44<18,C44>70),"Check","OK") -> OK
A45: CUST1043 | B45: Joseph Snow | C45: 45 | D45: Male | E45: South Michaelfort | F45: Vermont | G45: USA | H45: Gold | I45: =PROPER(B45) -> Joseph Snow | J45: =TRIM(PROPER(E45)) -> South Michaelfort | K45: =TRIM(PROPER(F45)) -> Vermont | L45: =TRIM(PROPER(D45)) -> Male | M45: =IF(H45="","Standard",H45) -> Gold | N45: =IF(OR(C45<18,C45>70),"Check","OK") -> OK
A46: CUST1044 | B46: Denise Williams | C46: 34 | D46: Male | E46: Christianstad | F46: Hawaii | G46: USA | H46: Bronze | I46: =PROPER(B46) -> Denise Williams | J46: =TRIM(PROPER(E46)) -> Christianstad | K46: =TRIM(PROPER(F46)) -> Hawaii | L46: =TRIM(PROPER(D46)) -> Male | M46: =IF(H46="","Standard",H46) -> Bronze | N46: =IF(OR(C46<18,C46>70),"Check","OK") -> OK
A47: CUST1045 | B47: Jordan Jackson DDS | C47: 54 | D47: Male | E47: North Johnview | F47: Arizona | G47: USA | H47: Gold | I47: =PROPER(B47) -> Jordan Jackson Dds | J47: =TRIM(PROPER(E47)) -> North Johnview | K47: =TRIM(PROPER(F47)) -> Arizona | L47: =TRIM(PROPER(D47)) -> Male | M47: =IF(H47="","Standard",H47) -> Gold | N47: =IF(OR(C47<18,C47>70),"Check","OK") -> OK
A48: CUST1046 | B48: Michelle Garcia DDS | C48: 55 | D48: Female | E48: Perezbury | F48: Ohio | G48: USA | H48: Platinum | I48: =PROPER(B48) -> Michelle Garcia Dds | J48: =TRIM(PROPER(E48)) -> Perezbury | K48: =TRIM(PROPER(F48)) -> Ohio | L48: =TRIM(PROPER(D48)) -> Female | M48: =IF(H48="","Standard",H48) -> Platinum | N48: =IF(OR(C48<18,C48>70),"Check","OK") -> OK
A49: CUST1047 | B49: Gina Knight | C49: 54 | D49: Female | E49: Lake Roberthaven | F49: Nevada | G49: USA | H49: Silver | I49: =PROPER(B49) -> Gina Knight | J49: =TRIM(PROPER(E49)) -> Lake Roberthaven | K49: =TRIM(PROPER(F49)) -> Nevada | L49: =TRIM(PROPER(D49)) -> Female | M49: =IF(H49="","Standard",H49) -> Silver | N49: =IF(OR(C49<18,C49>70),"Check","OK") -> OK
A50: CUST1048 | B50: April Mullins | C50: 54 | D50: Male | E50: Dawsonbury | F50: North Carolina | G50: USA | H50: Platinum | I50: =PROPER(B50) -> April Mullins | J50: =TRIM(PROPER(E50)) -> Dawsonbury | K50: =TRIM(PROPER(F50)) -> North Carolina | L50: =TRIM(PROPER(D50)) -> Male | M50: =IF(H50="","Standard",H50) -> Platinum | N50: =IF(OR(C50<18,C50>70),"Check","OK") -> OK
A51: CUST1049 | B51: Timothy Weaver | C51: 45 | D51: Female | E51: New Amy | F51: Ohio | G51: USA | H51: Gold | I51: =PROPER(B51) -> Timothy Weaver | J51: =TRIM(PROPER(E51)) -> New Amy | K51: =TRIM(PROPER(F51)) -> Ohio | L51: =TRIM(PROPER(D51)) -> Female | M51: =IF(H51="","Standard",H51) -> Gold | N51: =IF(OR(C51<18,C51>70),"Check","OK") -> OK
... A501: CUST1499 | B501: Philip Pennington | C501: 27 | D501: Female | E501: East Valerieview | F501: Oregon | G501: USA | H501: Platinum | I501: =PROPER(B501) -> Philip Pennington | J501: =TRIM(PROPER(E501)) -> East Valerieview | K501: =TRIM(PROPER(F501)) -> Oregon | L501: =TRIM(PROPER(D501)) -> Female | M501: =IF(H501="","Standard",H501) -> Platinum | N501: =IF(OR(C501<18,C501>70),"Check","OK") -> OK

Sheet Product_Dim
A1: Product_ID | B1: Product_Name | C1: Category | D1: Sub_Category | E1: Brand | F1: Cost | G1: Stock | I1: Clean_Product_Name | J1: Category_Filled | K1: Price_Check
A2: PROD0 | B2: Brother Laser Printer | C2: Electronics | D2: Computer | E2: Hunt Inc | F2: 112.42 | G2: 416 | I2: =PROPER(B2) -> Brother Laser Printer | J2: =IF(C2="","Others",C2) -> Electronics | K2: =IF(F2<=0,"Error","Valid") -> Valid
A3: PROD1 | B3: Men's Graphic T-Shirt | C3: Clothing | D3: Tops | E3: Terry-Moore | F3: 342.56 | G3: 181 | I3: =PROPER(B3) -> Men'S Graphic T-Shirt | J3: =IF(C3="","Others",C3) -> Clothing | K3: =IF(F3<=0,"Error","Valid") -> Valid
A4: PROD2 | B4: Women's Casual Hoodie | C4: Clothing | D4: Outerwear | E4: Sims Inc | G4: 352 | I4: =PROPER(B4) -> Women'S Casual Hoodie | J4: =IF(C4="","Others",C4) -> Clothing | K4: =IF(F4<=0,"Error","Valid") -> Error
A5: P-3 | B5: Men's Running Jacket | C5: Clothing | D5: Outerwear | E5: Pineda Ltd | F5: 364.67 | G5: 452 | I5: =PROPER(B5) -> Men'S Running Jacket | J5: =IF(C5="","Others",C5) -> Clothing | K5: =IF(F5<=0,"Error","Valid") -> Valid
A6: PROD4 | B6: Women's Yoga Pants | C6: Clothing | D6: Bottoms | E6: Gonzales-Davis | F6: 306.46 | G6: 487 | I6: =PROPER(B6) -> Women'S Yoga Pants | J6: =IF(C6="","Others",C6) -> Clothing | K6: =IF(F6<=0,"Error","Valid") -> Valid
A7: PROD5 | B7: Men's Leather Belt | C7: Clothing | D7: Accessories | E7: Baldwin, Garza and Gonzalez | F7: 261 | G7: 59 | I7: =PROPER(B7) -> Men'S Leather Belt | J7: =IF(C7="","Others",C7) -> Clothing | K7: =IF(F7<=0,"Error","Valid") -> Valid
A8: PROD6 | B8: Herbal Face Moisturizer | C8: Beauty | D8: Skincare | E8: Davidson PLC | F8: 312.8 | G8: 350 | I8: =PROPER(B8) -> Herbal Face Moisturizer | J8: =IF(C8="","Others",C8) -> Beauty | K8: =IF(F8<=0,"Error","Valid") -> Valid
A9: PROD7 | B9: LED Table Lamp | C9: Home | D9: Lighting | E9: Harrell LLC | F9: 218.86 | G9: 170 | I9: =PROPER(B9) -> Led Table Lamp | J9: =IF(C9="","Others",C9) -> Home | K9: =IF(F9<=0,"Error","Valid") -> Valid
A10: PROD8 | B10: Wireless Bluetooth Earbuds | C10: Electronics | D10: Audio | E10: Perez-Johnston | F10: 439.07 | G10: 142 | I10: =PROPER(B10) -> Wireless Bluetooth Earbuds | J10: =IF(C10="","Others",C10) -> Electronics | K10: =IF(F10<=0,"Error","Valid") -> Valid
A11: PROD9 | B11: Adjustable Dumbbell Set | C11: Sports | D11: Fitness | E11: Hill PLC | F11: 495.72 | G11: 323 | I11: =PROPER(B11) -> Adjustable Dumbbell Set | J11: =IF(C11="","Others",C11) -> Sports | K11: =IF(F11<=0,"Error","Valid") -> Valid
A12: PROD10 | B12: Ceramic Kitchen Bowl Set | C12: Home | D12: Kitchen | E12: Hamilton Group | F12: 298.86 | G12: 308 | I12: =PROPER(B12) -> Ceramic Kitchen Bowl Set | J12: =IF(C12="","Others",C12) -> Home | K12: =IF(F12<=0,"Error","Valid") -> Valid
A13: PROD11 | B13: HD Smart TV Stick | C13: Electronics | D13: Accessories | E13: Gibson, Hobbs and Weaver | F13: 449.4 | I13: =PROPER(B13) -> Hd Smart Tv Stick | J13: =IF(C13="","Others",C13) -> Electronics | K13: =IF(F13<=0,"Error","Valid") -> Valid
A14: PROD12 | B14: Hair Strengthening Shampoo | C14: Beauty | D14: Haircare | E14: Rice LLC | F14: 115.82 | G14: 460 | I14: =PROPER(B14) -> Hair Strengthening Shampoo | J14: =IF(C14="","Others",C14) -> Beauty | K14: =IF(F14<=0,"Error","Valid") -> Valid
A15: PROD13 | B15: USB-C Fast Charger | C15: Electronics | D15: Accessories | E15: Dawson-Perkins | F15: 242.23 | G15: 453 | I15: =PROPER(B15) -> Usb-C Fast Charger | J15: =IF(C15="","Others",C15) -> Electronics | K15: =IF(F15<=0,"Error","Valid") -> Valid
A16: PROD14 | B16: Decorative Wall Mirror | C16: Home | D16: Decor | E16: Luna, Anderson and Bowman | F16: 48.01 | G16: 439 | I16: =PROPER(B16) -> Decorative Wall Mirror | J16: =IF(C16="","Others",C16) -> Home | K16: =IF(F16<=0,"Error","Valid") -> Valid
A17: PROD15 | B17: 4K Home Projector | C17: Electronics | D17: Appliances | E17: Thomas LLC | F17: 465.34 | G17: 301 | I17: =PROPER(B17) -> 4K Home Projector | J17: =IF(C17="","Others",C17) -> Electronics | K17: =IF(F17<=0,"Error","Valid") -> Valid
A18: P-16 | B18: Beard Grooming Kit | C18: Beauty | D18: Grooming | E18: Erickson-Green | F18: 337.42 | G18: 256 | I18: =PROPER(B18) -> Beard Grooming Kit | J18: =IF(C18="","Others",C18) -> Beauty | K18: =IF(F18<=0,"Error","Valid") -> Valid
A19: PROD17 | B19: Soccer Training Cone Set | C19: Sports | D19: Accessories | E19: Ford, Murphy and Wilson | F19: 144.53 | G19: 367 | I19: =PROPER(B19) -> Soccer Training Cone Set | J19: =IF(C19="","Others",C19) -> Sports | K19: =IF(F19<=0,"Error","Valid") -> Valid
A20: PROD18 | B20: Women's Denim Jeans | C20: Clothing | D20: Bottoms | E20: Guerra-Hendrix | G20: 343 | I20: =PROPER(B20) -> Women'S Denim Jeans | J20: =IF(C20="","Others",C20) -> Clothing | K20: =IF(F20<=0,"Error","Valid") -> Error
A21: PROD19 | B21: Knee Support Brace | C21: Sports | D21: Equipment | E21: May-Reese | F21: 21.34 | G21: 65 | I21: =PROPER(B21) -> Knee Support Brace | J21: =IF(C21="","Others",C21) -> Sports | K21: =IF(F21<=0,"Error","Valid") -> Valid
A22: PROD20 | B22: Outdoor Sports Water Bottle | C22: Sports | D22: Accessories | E22: Soto-Ellis | F22: 131.51 | I22: =PROPER(B22) -> Outdoor Sports Water Bottle | J22: =IF(C22="","Others",C22) -> Sports | K22: =IF(F22<=0,"Error","Valid") -> Valid
A23: PROD21 | B23: Multi-Purpose Storage Box | C23: Home | D23: Storage | E23: Gardner-Montes | F23: 123.46 | G23: 76 | I23: =PROPER(B23) -> Multi-Purpose Storage Box | J23: =IF(C23="","Others",C23) -> Home | K23: =IF(F23<=0,"Error","Valid") -> Valid
A24: PROD22 | B24: Carbon Fiber Tennis Racket | C24: Sports | D24: Equipment | E24: Flores, Pineda and Rodriguez | F24: 484.62 | G24: 432 | I24: =PROPER(B24) -> Carbon Fiber Tennis Racket | J24: =IF(C24="","Others",C24) -> Sports | K24: =IF(F24<=0,"Error","Valid") -> Valid
A25: PROD23 | B25: Men's Formal Shirt | C25: Clothing | D25: Tops | E25: Moon, Mora and Santos | G25: 360 | I25: =PROPER(B25) -> Men'S Formal Shirt | J25: =IF(C25="","Others",C25) -> Clothing | K25: =IF(F25<=0,"Error","Valid") -> Error
A26: PROD24 | B26: Foldable Camping Chair | C26: Sports | D26: Outdoor | E26: Cook Ltd | F26: 166.06 | G26: 340 | I26: =PROPER(B26) -> Foldable Camping Chair | J26: =IF(C26="","Others",C26) -> Sports | K26: =IF(F26<=0,"Error","Valid") -> Valid
A27: PROD25 | B27: Women's Scarf Set | C27: Clothing | D27: Accessories | E27: Brown and Sons | F27: 174.02 | G27: 268 | I27: =PROPER(B27) -> Women'S Scarf Set | J27: =IF(C27="","Others",C27) -> Clothing | K27: =IF(F27<=0,"Error","Valid") -> Valid
A28: PROD26 | B28: Wireless Bluetooth Speaker | C28: Electronics | D28: Audio | E28: Reed-Schmidt | F28: 322.41 | G28: 213 | I28: =PROPER(B28) -> Wireless Bluetooth Speaker | J28: =IF(C28="","Others",C28) -> Electronics | K28: =IF(F28<=0,"Error","Valid") -> Valid
A29: PROD27 | B29: Decorative Floor Vase | C29: Home | D29: Decor | E29: Khan, Jones and Paul | G29: 378 | I29: =PROPER(B29) -> Decorative Floor Vase | J29: =IF(C29="","Others",C29) -> Home | K29: =IF(F29<=0,"Error","Valid") -> Error
A30: PROD28 | B30: Sports Stopwatch Timer | C30: Sports | D30: Accessories | E30: Burns-Hansen | F30: 38.76 | G30: 137 | I30: =PROPER(B30) -> Sports Stopwatch Timer | J30: =IF(C30="","Others",C30) -> Sports | K30: =IF(F30<=0,"Error","Valid") -> Valid
A31: PROD29 | B31: Fabric Sofa Throw Blanket | C31: Home | D31: Decor | E31: Hoffman Group | F31: 218.48 | G31: 276 | I31: =PROPER(B31) -> Fabric Sofa Throw Blanket | J31: =IF(C31="","Others",C31) -> Home | K31: =IF(F31<=0,"Error","Valid") -> Valid
A32: PROD30 | B32: Stainless Steel Cutlery Set | C32: Home | D32: Kitchen | E32: Stevens, Fernandez and Martin | F32: 19.52 | G32: 57 | I32: =PROPER(B32) -> Stainless Steel Cutlery Set | J32: =IF(C32="","Others",C32) -> Home | K32: =IF(F32<=0,"Error","Valid") -> Valid
A33: PROD31 | B33: Basketball | C33: Sports | D33: Team Sports | E33: Nolan-Snow | F33: 204.39 | G33: 281 | I33: =PROPER(B33) -> Basketball | J33: =IF(C33="","Others",C33) -> Sports | K33: =IF(F33<=0,"Error","Valid") -> Valid
A34: PROD32 | B34: Vitamin C Face Serum | C34: Beauty | D34: Skincare | E34: Griffin Ltd | F34: 283.83 | G34: 244 | I34: =PROPER(B34) -> Vitamin C Face Serum | J34: =IF(C34="","Others",C34) -> Beauty | K34: =IF(F34<=0,"Error","Valid") -> Valid
A35: PROD33 | B35: Modern Wall Clock | C35: Home | D35: Decor | E35: Weiss-Watson | F35: 179.77 | G35: 305 | I35: =PROPER(B35) -> Modern Wall Clock | J35: =IF(C35="","Others",C35) -> Home | K35: =IF(F35<=0,"Error","Valid") -> Valid
A36: PROD34 | B36: Gaming Mechanical Keyboard | C36: Electronics | D36: Computer | E36: Lucero LLC | F36: 419.28 | G36: 86 | I36: =PROPER(B36) -> Gaming Mechanical Keyboard | J36: =IF(C36="","Others",C36) -> Electronics | K36: =IF(F36<=0,"Error","Valid") -> Valid
A37: PROD35 | B37: Bedroom Table Lamp | C37: Home | D37: Lighting | E37: Jones LLC | F37: 382.22 | G37: 329 | I37: =PROPER(B37) -> Bedroom Table Lamp | J37: =IF(C37="","Others",C37) -> Home | K37: =IF(F37<=0,"Error","Valid") -> Valid
A38: PROD36 | B38: Women's Summer Dress | C38: Clothing | D38: Tops | E38: Smith-Mills | F38: 223.43 | G38: 154 | I38: =PROPER(B38) -> Women'S Summer Dress | J38: =IF(C38="","Others",C38) -> Clothing | K38: =IF(F38<=0,"Error","Valid") -> Valid
A39: PROD37 | B39: Men's Casual Sneakers | C39: Clothing | D39: Footwear | E39: Hogan-Lee | F39: 353.47 | G39: 214 | I39: =PROPER(B39) -> Men'S Casual Sneakers | J39: =IF(C39="","Others",C39) -> Clothing | K39: =IF(F39<=0,"Error","Valid") -> Valid
A40: PROD38 | B40: Sports Water Hydration Pack | C40: Sports | D40: Outdoor | E40: Sims-Smith | F40: 135.61 | G40: 394 | I40: =PROPER(B40) -> Sports Water Hydration Pack | J40: =IF(C40="","Others",C40) -> Sports | K40: =IF(F40<=0,"Error","Valid") -> Valid
A41: PROD39 | B41: Portable Power Bank | C41: Electronics | D41: Mobile | E41: Cummings and Sons | F41: 326.06 | G41: 301 | I41: =PROPER(B41) -> Portable Power Bank | J41: =IF(C41="","Others",C41) -> Electronics | K41: =IF(F41<=0,"Error","Valid") -> Valid
... A48: PROD46 | B48: Men's Winter Jacket | C48: Clothing | D48: Outerwear | E48: Kelly, Smith and Perez | F48: 167.34 | G48: 296 | I48: =PROPER(B48) -> Men'S Winter Jacket | J48: =IF(C48="","Others",C48) -> Clothing | K48: =IF(F48<=0,"Error","Valid") -> Valid
A49: PROD47 | B49: Makeup Brush Set | C49: Beauty | D49: Makeup | E49: Cook Inc | G49: 431 | I49: =PROPER(B49) -> Makeup Brush Set | J49: =IF(C49="","Others",C49) -> Beauty | K49: =IF(F49<=0,"Error","Valid") -> Error
A50: PROD48 | B50: Car Dashboard Phone Holder | C50: Electronics | D50: Accessories | E50: Byrd, Stewart and Valdez | F50: 177.98 | G50: 103 | I50: =PROPER(B50) -> Car Dashboard Phone Holder | J50: =IF(C50="","Others",C50) -> Electronics | K50: =IF(F50<=0,"Error","Valid") -> Valid
A51: PROD49 | B51: Men's Roll-On Perfume | C51: Beauty | D51: Fragrance | E51: Sullivan and Sons | F51: 43.29 | G51: 267 | I51: =PROPER(B51) -> Men'S Roll-On Perfume | J51: =IF(C51="","Others",C51) -> Beauty | K51: =IF(F51<=0,"Error","Valid") -> Valid
A52: PROD50 | B52: Boxing Hand Wraps | C52: Sports | D52: Fitness | E52: Smith-King | F52: 190.29 | G52: 260 | I52: =PROPER(B52) -> Boxing Hand Wraps | J52: =IF(C52="","Others",C52) -> Sports | K52: =IF(F52<=0,"Error","Valid") -> Valid
A53: PROD51 | B53: HDMI Cable – 2m | C53: Electronics | D53: Accessories | E53: Bautista, Green and Hale | F53: 88.49 | G53: 246 | I53: =PROPER(B53) -> Hdmi Cable – 2M | J53: =IF(C53="","Others",C53) -> Electronics | K53: =IF(F53<=0,"Error","Valid") -> Valid
A54: PROD52 | B54: Rugby Ball | C54: Sports | D54: Team Sports | E54: Harris Inc | F54: 212.26 | G54: 82 | I54: =PROPER(B54) -> Rugby Ball | J54: =IF(C54="","Others",C54) -> Sports | K54: =IF(F54<=0,"Error","Valid") -> Valid
A55: PROD53 | B55: Men's Track Pants | C55: Clothing | D55: Bottoms | E55: Hamilton, Woods and Walker | F55: 386.56 | G55: 125 | I55: =PROPER(B55) -> Men'S Track Pants | J55: =IF(C55="","Others",C55) -> Clothing | K55: =IF(F55<=0,"Error","Valid") -> Valid
A56: PROD54 | B56: Sports Stopwatch Pro | C56: Sports | D56: Accessories | E56: Thompson-French | F56: 434.84 | G56: 185 | I56: =PROPER(B56) -> Sports Stopwatch Pro | J56: =IF(C56="","Others",C56) -> Sports | K56: =IF(F56<=0,"Error","Valid") -> Valid
A57: PROD55 | B57: Ceramic Plant Pot | C57: Home | D57: Decor | E57: Hatfield, Baird and Torres | F57: 81.75 | I57: =PROPER(B57) -> Ceramic Plant Pot | J57: =IF(C57="","Others",C57) -> Home | K57: =IF(F57<=0,"Error","Valid") -> Valid
A58: PROD56 | B58: Premium Blanket Throw | C58: Home | D58: Decor | E58: Hernandez, Kennedy and Porter | F58: 461.47 | G58: 190 | I58: =PROPER(B58) -> Premium Blanket Throw | J58: =IF(C58="","Others",C58) -> Home | K58: =IF(F58<=0,"Error","Valid") -> Valid
A59: PROD57 | B59: Foam Roller | C59: Sports | D59: Fitness | E59: Atkinson, Camacho and Oliver | F59: 30.62 | G59: 138 | I59: =PROPER(B59) -> Foam Roller | J59: =IF(C59="","Others",C59) -> Sports | K59: =IF(F59<=0,"Error","Valid") -> Valid
A60: PROD58 | B60: Womens Cotton Scarf | C60: Clothing | D60: Accessories | E60: Shepherd-Gould | F60: 113.83 | G60: 485 | I60: =PROPER(B60) -> Womens Cotton Scarf | J60: =IF(C60="","Others",C60) -> Clothing | K60: =IF(F60<=0,"Error","Valid") -> Valid
A61: PROD59 | B61: Men's Hair Styling Gel | C61: Beauty | D61: Haircare | E61: Cline-Mccarthy | F61: 17.31 | G61: 399 | I61: =PROPER(B61) -> Men'S Hair Styling Gel | J61: =IF(C61="","Others",C61) -> Beauty | K61: =IF(F61<=0,"Error","Valid") -> Valid
A62: PROD60 | B62: Luxury Perfume Spray | C62: Beauty | D62: Fragrance | E62: Gibson, Green and Lopez | F62: 482.75 | G62: 444 | I62: =PROPER(B62) -> Luxury Perfume Spray | J62: =IF(C62="","Others",C62) -> Beauty | K62: =IF(F62<=0,"Error","Valid") -> Valid
A63: PROD61 | B63: Tennis Ball 3-Pack | C63: Sports | D63: Equipment | E63: Lopez LLC | F63: 103.45 | G63: 465 | I63: =PROPER(B63) -> Tennis Ball 3-Pack | J63: =IF(C63="","Others",C63) -> Sports | K63: =IF(F63<=0,"Error","Valid") -> Valid
A64: PROD62 | B64: Laptop Cooling Pad | C64: Electronics | D64: Computer | E64: Murray, Gould and Ware | F64: 86.42 | G64: 222 | I64: =PROPER(B64) -> Laptop Cooling Pad | J64: =IF(C64="","Others",C64) -> Electronics | K64: =IF(F64<=0,"Error","Valid") -> Valid
A65: PROD63 | B65: Organic Sunscreen Lotion | C65: Beauty | D65: Skincare | E65: Anderson-Riley | F65: 266.86 | G65: 458 | I65: =PROPER(B65) -> Organic Sunscreen Lotion | J65: =IF(C65="","Others",C65) -> Beauty | K65: =IF(F65<=0,"Error","Valid") -> Valid
A66: PROD64 | B66: Matte Lipstick Set | C66: Beauty | D66: Makeup | E66: Zhang Inc | F66: 299.11 | G66: 118 | I66: =PROPER(B66) -> Matte Lipstick Set | J66: =IF(C66="","Others",C66) -> Beauty | K66: =IF(F66<=0,"Error","Valid") -> Valid
A67: PROD65 | B67: Adjustable Dumbbells 20kg | C67: Sports | D67: Fitness | E67: Montgomery, Benton and Miller | F67: 240.63 | G67: 423 | I67: =PROPER(B67) -> Adjustable Dumbbells 20Kg | J67: =IF(C67="","Others",C67) -> Sports | K67: =IF(F67<=0,"Error","Valid") -> Valid
A68: PROD66 | B68: Women's Hair Dryer Brush | C68: Beauty | D68: Haircare | E68: Torres, Spencer and Potter | F68: 340.39 | G68: 177 | I68: =PROPER(B68) -> Women'S Hair Dryer Brush | J68: =IF(C68="","Others",C68) -> Beauty | K68: =IF(F68<=0,"Error","Valid") -> Valid
A69: PROD67 | B69: Smart LED Light Strip | C69: Electronics | D69: Accessories | E69: Flores-Davis | F69: 349.17 | G69: 476 | I69: =PROPER(B69) -> Smart Led Light Strip | J69: =IF(C69="","Others",C69) -> Electronics | K69: =IF(F69<=0,"Error","Valid") -> Valid
... A84: PROD82 | B84: Fitness Resistance Bands | C84: Sports | D84: Fitness | E84: Reese-Watson | F84: 152.92 | G84: 281 | I84: =PROPER(B84) -> Fitness Resistance Bands | J84: =IF(C84="","Others",C84) -> Sports | K84: =IF(F84<=0,"Error","Valid") -> Valid
A85: PROD83 | B85: Hydrating Face Cleanser | C85: Beauty | D85: Skincare | E85: Butler Group | G85: 159 | I85: =PROPER(B85) -> Hydrating Face Cleanser | J85: =IF(C85="","Others",C85) -> Beauty | K85: =IF(F85<=0,"Error","Valid") -> Error
A86: PROD84 | B86: Wooden Bookshelf | C86: Home | D86: Furniture | E86: Collins-Stephenson | F86: 388.46 | G86: 208 | I86: =PROPER(B86) -> Wooden Bookshelf | J86: =IF(C86="","Others",C86) -> Home | K86: =IF(F86<=0,"Error","Valid") -> Valid
A87: PROD85 | B87: Women's Beanie Hat | C87: Clothing | D87: Accessories | E87: Richardson-Carrillo | F87: 119.57 | G87: 210 | I87: =PROPER(B87) -> Women'S Beanie Hat | J87: =IF(C87="","Others",C87) -> Clothing | K87: =IF(F87<=0,"Error","Valid") -> Valid
A88: PROD86 | B88: Kitchen Cutting Board | C88: Home | D88: Kitchen | E88: Taylor, Dodson and Johnston | F88: 176.07 | G88: 82 | I88: =PROPER(B88) -> Kitchen Cutting Board | J88: =IF(C88="","Others",C88) -> Home | K88: =IF(F88<=0,"Error","Valid") -> Valid
A89: PROD87 | B89: LED Bedside Lamp | C89: Home | D89: Lighting | E89: Aguilar, Horton and Lewis | F89: 371.38 | G89: 220 | I89: =PROPER(B89) -> Led Bedside Lamp | J89: =IF(C89="","Others",C89) -> Home | K89: =IF(F89<=0,"Error","Valid") -> Valid
A90: PROD88 | B90: Sports Wrist Sweatbands | C90: Sports | D90: Accessories | E90: Olsen-Daniels | F90: 131.24 | G90: 232 | I90: =PROPER(B90) -> Sports Wrist Sweatbands | J90: =IF(C90="","Others",C90) -> Sports | K90: =IF(F90<=0,"Error","Valid") -> Valid
A91: PROD89 | B91: Face Foundation Kit | C91: Beauty | D91: Makeup | E91: Taylor-Elliott | F91: 183.04 | G91: 457 | I91: =PROPER(B91) -> Face Foundation Kit | J91: =IF(C91="","Others",C91) -> Beauty | K91: =IF(F91<=0,"Error","Valid") -> Valid
A92: PROD90 | B92: Gaming Mouse Pad XL | C92: Electronics | D92: Accessories | E92: Sharp, Taylor and Rodriguez | F92: 340.14 | G92: 361 | I92: =PROPER(B92) -> Gaming Mouse Pad Xl | J92: =IF(C92="","Others",C92) -> Electronics | K92: =IF(F92<=0,"Error","Valid") -> Valid
A93: PROD91 | B93: Women's High Heels | C93: Clothing | D93: Footwear | E93: Smith-Charles | F93: 438.25 | G93: 496 | I93: =PROPER(B93) -> Women'S High Heels | J93: =IF(C93="","Others",C93) -> Clothing | K93: =IF(F93<=0,"Error","Valid") -> Valid
A94: PROD92 | B94: Microwave Oven | C94: Home | D94: Appliances | E94: Green, Powell and Palmer | F94: 447.43 | G94: 191 | I94: =PROPER(B94) -> Microwave Oven | J94: =IF(C94="","Others",C94) -> Home | K94: =IF(F94<=0,"Error","Valid") -> Valid
A95: PROD93 | B95: USB-C Laptop Charger | C95: Electronics | D95: Computer | E95: Martin LLC | F95: 377.52 | G95: 485 | I95: =PROPER(B95) -> Usb-C Laptop Charger | J95: =IF(C95="","Others",C95) -> Electronics | K95: =IF(F95<=0,"Error","Valid") -> Valid
A96: PROD94 | B96: Vitamin E Body Lotion | C96: Beauty | D96: Skincare | E96: Hoffman-Williams | F96: 358.47 | G96: 213 | I96: =PROPER(B96) -> Vitamin E Body Lotion | J96: =IF(C96="","Others",C96) -> Beauty | K96: =IF(F96<=0,"Error","Valid") -> Valid
A97: PROD95 | B97: Sports Stopwatch Basic | C97: Sports | D97: Accessories | E97: Wilson Group | F97: 60.65 | G97: 75 | I97: =PROPER(B97) -> Sports Stopwatch Basic | J97: =IF(C97="","Others",C97) -> Sports | K97: =IF(F97<=0,"Error","Valid") -> Valid
... A101: PROD99 | B101: Stainless Steel Cookware Set | C101: Home | D101: Kitchen | E101: Campbell Ltd | F101: 201.41 | G101: 146 | I101: =PROPER(B101) -> Stainless Steel Cookware Set | J101: =IF(C101="","Others",C101) -> Home | K101: =IF(F101<=0,"Error","Valid") -> Valid

Sheet Store_Dim
A1: Store_ID | B1: Region | C1: City | D1: Store_Type | F1: Clean_Store_ID | G1: Store_ID_Length | H1: Region_Store_Count | I1: Store_Key | J1: Validation
A2: STORE0 | B2: East | C2: Washingtonfurt | D2: Flagship | F2: =UPPER(TRIM(A2)) -> STORE0 | G2: =LEN(A2) -> 6 | H2: =COUNTIF(B:B,B2) -> 6 | I2: =A2&"-"&C2 -> STORE0-Washingtonfurt | J2: =IF(A2="","Missing ID","OK") -> OK
A3: STORE1 | B3: North | C3: Danielmouth | D3: Flagship | F3: =UPPER(TRIM(A3)) -> STORE1 | G3: =LEN(A3) -> 6 | H3: =COUNTIF(B:B,B3) -> 6 | I3: =A3&"-"&C3 -> STORE1-Danielmouth | J3: =IF(A3="","Missing ID","OK") -> OK
A4: STORE2 | B4: South | C4: North Nancyview | D4: Outlet | F4: =UPPER(TRIM(A4)) -> STORE2 | G4: =LEN(A4) -> 6 | H4: =COUNTIF(B:B,B4) -> 6 | I4: =A4&"-"&C4 -> STORE2-North Nancyview | J4: =IF(A4="","Missing ID","OK") -> OK
A5: STORE3 | B5: North | C5: Hoodberg | D5: Outlet | F5: =UPPER(TRIM(A5)) -> STORE3 | G5: =LEN(A5) -> 6 | H5: =COUNTIF(B:B,B5) -> 6 | I5: =A5&"-"&C5 -> STORE3-Hoodberg | J5: =IF(A5="","Missing ID","OK") -> OK
A6: STORE4 | B6: South | C6: Port Sharon | D6: Online | F6: =UPPER(TRIM(A6)) -> STORE4 | G6: =LEN(A6) -> 6 | H6: =COUNTIF(B:B,B6) -> 6 | I6: =A6&"-"&C6 -> STORE4-Port Sharon | J6: =IF(A6="","Missing ID","OK") -> OK
A7: STORE5 | B7: North | C7: New Michaelchester | D7: Outlet | F7: =UPPER(TRIM(A7)) -> STORE5 | G7: =LEN(A7) -> 6 | H7: =COUNTIF(B:B,B7) -> 6 | I7: =A7&"-"&C7 -> STORE5-New Michaelchester | J7: =IF(A7="","Missing ID","OK") -> OK
A8: STORE6 | B8: East | C8: Port Josephberg | D8: Online | F8: =UPPER(TRIM(A8)) -> STORE6 | G8: =LEN(A8) -> 6 | H8: =COUNTIF(B:B,B8) -> 6 | I8: =A8&"-"&C8 -> STORE6-Port Josephberg | J8: =IF(A8="","Missing ID","OK") -> OK
A9: STORE7 | B9: South | C9: Williamsfurt | D9: Online | F9: =UPPER(TRIM(A9)) -> STORE7 | G9: =LEN(A9) -> 6 | H9: =COUNTIF(B:B,B9) -> 6 | I9: =A9&"-"&C9 -> STORE7-Williamsfurt | J9: =IF(A9="","Missing ID","OK") -> OK
A10: STORE8 | B10: West | C10: Thompsonborough | D10: Online | F10: =UPPER(TRIM(A10)) -> STORE8 | G10: =LEN(A10) -> 6 | H10: =COUNTIF(B:B,B10) -> 2 | I10: =A10&"-"&C10 -> STORE8-Thompsonborough | J10: =IF(A10="","Missing ID","OK") -> OK
A11: STORE9 | B11: South | C11: East Johnstad | D11: Flagship | F11: =UPPER(TRIM(A11)) -> STORE9 | G11: =LEN(A11) -> 6 | H11: =COUNTIF(B:B,B11) -> 6 | I11: =A11&"-"&C11 -> STORE9-East Johnstad | J11: =IF(A11="","Missing ID","OK") -> OK
A12: STORE10 | B12: East | C12: East Davidville | D12: Online | F12: =UPPER(TRIM(A12)) -> STORE10 | G12: =LEN(A12) -> 7 | H12: =COUNTIF(B:B,B12) -> 6 | I12: =A12&"-"&C12 -> STORE10-East Davidville | J12: =IF(A12="","Missing ID","OK") -> OK
A13: STORE11 | B13: South | C13: Lake Michael | D13: Online | F13: =UPPER(TRIM(A13)) -> STORE11 | G13: =LEN(A13) -> 7 | H13: =COUNTIF(B:B,B13) -> 6 | I13: =A13&"-"&C13 -> STORE11-Lake Michael | J13: =IF(A13="","Missing ID","OK") -> OK
... A21: STORE19 | B21: East | C21: Vasquezborough | D21: Online | F21: =UPPER(TRIM(A21)) -> STORE19 | G21: =LEN(A21) -> 7 | H21: =COUNTIF(B:B,B21) -> 6 | I21: =A21&"-"&C21 -> STORE19-Vasquezborough | J21: =IF(A21="","Missing ID","OK") -> OK

Sheet Sales_Fact
A1: Sales_ID | B1: Order_Date | C1: Customer_ID | D1: Product_ID | E1: Store_ID | F1: Quantity | G1: Unit_Price | H1: Discount | I1: Total_Amount | J1: Net_Sales | K1: Month | L1: Year | N1: Customer_Name | O1: City | P1: Product_Name | Q1: Category | R1: Region | S1: Store_Type
A2: SALE0 | B2: 45480 | C2: CUST1409 | D2: PROD97 | E2: STORE3 | F2: 1 | G2: 218.04 | H2: 0.09 | I2: =F2*G2 -> 218.04 | J2: =H2*(1-I2) -> -19.5336 | K2: =TEXT(B2,"mmm") -> Jul | L2: =YEAR(B2) -> 2024 | N2: {=XLOOKUP(C2,Customer_Dim!A:A,Customer_Dim!B:B,"Not Found")} -> Sarah Smith | O2: {=XLOOKUP(C2,Customer_Dim!A:A,Customer_Dim!E:E,"Not Found")} -> Kathleenport | P2: {=XLOOKUP(D2,Product_Dim!A:A,Product_Dim!B:B,"Not Found")} -> Cricket Bat | Q2: {=XLOOKUP(D2,Product_Dim!A:A,Product_Dim!C:C,"Not Found")} -> Sports | R2: {=XLOOKUP(E2,Store_Dim!A:A,Store_Dim!B:B,"Not Found")} -> North | S2: {=XLOOKUP(E2,Store_Dim!A:A,Store_Dim!D:D,"Not Found")} -> Outlet
A3: SALE1 | B3: 45481 | C3: CUST1467 | D3: PROD74 | E3: STORE17 | F3: 3 | G3: 104.47 | H3: 0.27 | I3: =F3*G3 -> 313.41 | J3: =H3*(1-I3) -> -84.3507 | K3: =TEXT(B3,"mmm") -> Jul | L3: =YEAR(B3) -> 2024 | N3: {=XLOOKUP(C3,Customer_Dim!A:A,Customer_Dim!B:B,"Not Found")} -> Michael Foley | O3: {=XLOOKUP(C3,Customer_Dim!A:A,Customer_Dim!E:E,"Not Found")} -> Oneillfurt | P3: {=XLOOKUP(D3,Product_Dim!A:A,Product_Dim!B:B,"Not Found")} -> Bluetooth Car Audio System | Q3: {=XLOOKUP(D3,Product_Dim!A:A,Product_Dim!C:C,"Not Found")} -> Electronics | R3: {=XLOOKUP(E3,Store_Dim!A:A,Store_Dim!B:B,"Not Found")} -> North | S3: {=XLOOKUP(E3,Store_Dim!A:A,Store_Dim!D:D,"Not Found")} -> Flagship
A4: SALE2 | B4: 45482 | C4: CUST1056 | D4: PROD49 | E4: STORE8 | F4: 4 | G4: 914.05 | H4: 0.25 | I4: =F4*G4 -> 3656.2 | J4: =H4*(1-I4) -> -913.8 | K4: =TEXT(B4,"mmm") -> Jul | L4: =YEAR(B4) -> 2024 | N4: {=XLOOKUP(C4,Customer_Dim!A:A,Customer_Dim!B:B,"Not Found")} -> Christopher Sutton | O4: {=XLOOKUP(C4,Customer_Dim!A:A,Customer_Dim!E:E,"Not Found")} -> Deborahberg | P4: {=XLOOKUP(D4,Product_Dim!A:A,Product_Dim!B:B,"Not Found")} -> Men's Roll-On Perfume | Q4: {=XLOOKUP(D4,Product_Dim!A:A,Product_Dim!C:C,"Not Found")} -> Beauty | R4: {=XLOOKUP(E4,Store_Dim!A:A,Store_Dim!B:B,"Not Found")} -> West | S4: {=XLOOKUP(E4,Store_Dim!A:A,Store_Dim!D:D,"Not Found")} -> Online
A5: SALE3 | B5: 45483 | C5: CUST1346 | D5: PROD76 | E5: STORE8 | F5: 1 | G5: 921.51 | H5: 0.16 | I5: =F5*G5 -> 921.51 | J5: =H5*(1-I5) -> -147.2816 | K5: =TEXT(B5,"mmm") -> Jul | L5: =YEAR(B5) -> 2024 | N5: {=XLOOKUP(C5,Customer_Dim!A:A,Customer_Dim!B:B,"Not Found")} -> John Jordan | O5: {=XLOOKUP(C5,Customer_Dim!A:A,Customer_Dim!E:E,"Not Found")} -> Port Crystalberg | P5: {=XLOOKUP(D5,Product_Dim!A:A,Product_Dim!B:B,"Not Found")} -> Wireless Mouse | Q5: {=XLOOKUP(D5,Product_Dim!A:A,Product_Dim!C:C,"Not Found")} -> Electronics | R5: {=XLOOKUP(E5,Store_Dim!A:A,Store_Dim!B:B,"Not Found")} -> West | S5: {=XLOOKUP(E5,Store_Dim!A:A,Store_Dim!D:D,"Not Found")} -> Online
A6: SALE4 | B6: 45484 | C6: CUST1493 | D6: PROD59 | E6: STORE5 | F6: 3 | G6: 745.3 | H6: 0.18 | I6: =F6*G6 -> 2235.9 | J6: =H6*(1-I6) -> -402.282 | K6: =TEXT(B6,"mmm") -> Jul | L6: =YEAR(B6) -> 2024 | N6: {=XLOOKUP(C6,Customer_Dim!A:A,Customer_Dim!B:B,"Not Found")} -> Amanda Powell | O6: {=XLOOKUP(C6,Customer_Dim!A:A,Customer_Dim!E:E,"Not Found")} -> South William | P6: {=XLOOKUP(D6,Product_Dim!A:A,Product_Dim!B:B,"Not Found")} -> Men's Hair Styling Gel | Q6: {=XLOOKUP(D6,Product_Dim!A:A,Product_Dim!C:C,"Not Found")} -> Beauty | R6: {=XLOOKUP(E6,Store_Dim!A:A,Store_Dim!B:B,"Not Found")} -> North | S6: {=XLOOKUP(E6,Store_Dim!A:A,Store_Dim!D:D,"Not Found")} -> Outlet
A7: SALE5 | B7: 45485 | C7: CUST1116 | D7: PROD15 | E7: STORE7 | F7: 3 | G7: 147.01 | H7: 0.19 | I7: =F7*G7 -> 441.03 | J7: =H7*(1-I7) -> -83.6057 | K7: =TEXT(B7,"mmm") -> Jul | L7: =YEAR(B7) -> 2024 | N7: {=XLOOKUP(C7,Customer_Dim!A:A,Customer_Dim!B:B,"Not Found")} -> Anthony Phillips | O7: {=XLOOKUP(C7,Customer_Dim!A:A,Customer_Dim!E:E,"Not Found")} -> North Davidport | P7: {=XLOOKUP(D7,Product_Dim!A:A,Product_Dim!B:B,"Not Found")} -> 4K Home Projector | Q7: {=XLOOKUP(D7,Product_Dim!A:A,Product_Dim!C:C,"Not Found")} -> Electronics | R7: {=XLOOKUP(E7,Store_Dim!A:A,Store_Dim!B:B,"Not Found")} -> South | S7: {=XLOOKUP(E7,Store_Dim!A:A,Store_Dim!D:D,"Not Found")} -> Online
A8: SALE6 | B8: 45486 | C8: CUST1016 | D8: PROD56 | E8: STORE4 | F8: 2 | G8: 785.31 | H8: 0.15 | I8: =F8*G8 -> 1570.62 | J8: =H8*(1-I8) -> -235.443 | K8: =TEXT(B8,"mmm") -> Jul | L8: =YEAR(B8) -> 2024 | N8: {=XLOOKUP(C8,Customer_Dim!A:A,Customer_Dim!B:B,"Not Found")} -> John Scott | O8: {=XLOOKUP(C8,Customer_Dim!A:A,Customer_Dim!E:E,"Not Found")} -> South Christopher | P8: {=XLOOKUP(D8,Product_Dim!A:A,Product_Dim!B:B,"Not Found")} -> Premium Blanket Throw | Q8: {=XLOOKUP(D8,Product_Dim!A:A,Product_Dim!C:C,"Not Found")} -> Home | R8: {=XLOOKUP(E8,Store_Dim!A:A,Store_Dim!B:B,"Not Found")} -> South | S8: {=XLOOKUP(E8,Store_Dim!A:A,Store_Dim!D:D,"Not Found")} -> Online
A9: SALE7 | B9: 45487 | C9: CUST1152 | D9: PROD70 | E9: STORE8 | F9: 4 | G9: 342.39 | H9: 0.23 | I9: =F9*G9 -> 1369.56 | J9: =H9*(1-I9) -> -314.7688 | K9: =TEXT(B9,"mmm") -> Jul | L9: =YEAR(B9) -> 2024 | N9: {=XLOOKUP(C9,Customer_Dim!A:A,Customer_Dim!B:B,"Not Found")} -> Patrick Roberts | O9: {=XLOOKUP(C9,Customer_Dim!A:A,Customer_Dim!E:E,"Not Found")} -> Jaredville | P9: {=XLOOKUP(D9,Product_Dim!A:A,Product_Dim!B:B,"Not Found")} -> Kitchen Storage Rack | Q9: {=XLOOKUP(D9,Product_Dim!A:A,Product_Dim!C:C,"Not Found")} -> Home | R9: {=XLOOKUP(E9,Store_Dim!A:A,Store_Dim!B:B,"Not Found")} -> West | S9: {=XLOOKUP(E9,Store_Dim!A:A,Store_Dim!D:D,"Not Found")} -> Online
A10: SALE8 | B10: 45488 | C10: CUST1187 | D10: PROD99 | E10: STORE5 | G10: 448.25 | H10: 0.07 | I10: =F10*G10 -> 0 | J10: =H10*(1-I10) -> 0.07 | K10: =TEXT(B10,"mmm") -> Jul | L10: =YEAR(B10) -> 2024 | N10: {=XLOOKUP(C10,Customer_Dim!A:A,Customer_Dim!B:B,"Not Found")} -> Dr. Suzanne Bullock | O10: {=XLOOKUP(C10,Customer_Dim!A:A,Customer_Dim!E:E,"Not Found")} -> Lake Blaketon | P10: {=XLOOKUP(D10,Product_Dim!A:A,Product_Dim!B:B,"Not Found")} -> Stainless Steel Cookware Set | Q10: {=XLOOKUP(D10,Product_Dim!A:A,Product_Dim!C:C,"Not Found")} -> Home | R10: {=XLOOKUP(E10,Store_Dim!A:A,Store_Dim!B:B,"Not Found")} -> North | S10: {=XLOOKUP(E10,Store_Dim!A:A,Store_Dim!D:D,"Not Found")} -> Outlet
A11: SALE9 | B11: 45489 | C11: CUST1464 | D11: PROD33 | E11: STORE0 | F11: 2 | G11: 873.17 | H11: 0.23 | I11: =F11*G11 -> 1746.34 | J11: =H11*(1-I11) -> -401.4282 | K11: =TEXT(B11,"mmm") -> Jul | L11: =YEAR(B11) -> 2024 | N11: {=XLOOKUP(C11,Customer_Dim!A:A,Customer_Dim!B:B,"Not Found")} -> David Pierce | O11: {=XLOOKUP(C11,Customer_Dim!A:A,Customer_Dim!E:E,"Not Found")} -> Grayland | P11: {=XLOOKUP(D11,Product_Dim!A:A,Product_Dim!B:B,"Not Found")} -> Modern Wall Clock | Q11: {=XLOOKUP(D11,Product_Dim!A:A,Product_Dim!C:C,"Not Found")} -> Home | R11: {=XLOOKUP(E11,Store_Dim!A:A,Store_Dim!B:B,"Not Found")} -> East | S11: {=XLOOKUP(E11,Store_Dim!A:A,Store_Dim!D:D,"Not Found")} -> Flagship
A12: SALE10 | B12: 45490 | C12: CUST1065 | D12: PROD24 | E12: STORE14 | F12: 1 | G12: 278.63 | H12: 0.07 | I12: =F12*G12 -> 278.63 | J12: =H12*(1-I12) -> -19.4341 | K12: =TEXT(B12,"mmm") -> Jul | L12: =YEAR(B12) -> 2024 | N12: {=XLOOKUP(C12,Customer_Dim!A:A,Customer_Dim!B:B,"Not Found")} -> Michael Thomas | O12: {=XLOOKUP(C12,Customer_Dim!A:A,Customer_Dim!E:E,"Not Found")} -> Woodmouth | P12: {=XLOOKUP(D12,Product_Dim!A:A,Product_Dim!B:B,"Not Found")} -> Foldable Camping Chair | Q12: {=XLOOKUP(D12,Product_Dim!A:A,Product_Dim!C:C,"Not Found")} -> Sports | R12: {=XLOOKUP(E12,Store_Dim!A:A,Store_Dim!B:B,"Not Found")} -> South | S12: {=XLOOKUP(E12,Store_Dim!A:A,Store_Dim!D:D,"Not Found")} -> Outlet
A13: SALE11 | B13: 45491 | C13: CUST1320 | D13: PROD39 | E13: STORE1 | F13: 4 | G13: 286.92 | H13: 0.17 | I13: =F13*G13 -> 1147.68 | J13: =H13*(1-I13) -> -194.9356 | K13: =TEXT(B13,"mmm") -> Jul | L13: =YEAR(B13) -> 2024 | N13: {=XLOOKUP(C13,Customer_Dim!A:A,Customer_Dim!B:B,"Not Found")} -> Jessica Gonzalez | O13: {=XLOOKUP(C13,Customer_Dim!A:A,Customer_Dim!E:E,"Not Found")} -> South Darrenland | P13: {=XLOOKUP(D13,Product_Dim!A:A,Product_Dim!B:B,"Not Found")} -> Portable Power Bank | Q13: {=XLOOKUP(D13,Product_Dim!A:A,Product_Dim!C:C,"Not Found")} -> Electronics | R13: {=XLOOKUP(E13,Store_Dim!A:A,Store_Dim!B:B,"Not Found")} -> North | S13: {=XLOOKUP(E13,Store_Dim!A:A,Store_Dim!D:D,"Not Found")} -> Flagship
A14: SALE12 | B14: 45492 | C14: CUST1237 | D14: PROD88 | E14: STORE4 | F14: 4 | G14: 644.58 | H14: 0.01 | I14: =F14*G14 -> 2578.32 | J14: =H14*(1-I14) -> -25.7732 | K14: =TEXT(B14,"mmm") -> Jul | L14: =YEAR(B14) -> 2024 | N14: {=XLOOKUP(C14,Customer_Dim!A:A,Customer_Dim!B:B,"Not Found")} -> Wesley Short | O14: {=XLOOKUP(C14,Customer_Dim!A:A,Customer_Dim!E:E,"Not Found")} -> Susanstad | P14: {=XLOOKUP(D14,Product_Dim!A:A,Product_Dim!B:B,"Not Found")} -> Sports Wrist Sweatbands | Q14: {=XLOOKUP(D14,Product_Dim!A:A,Product_Dim!C:C,"Not Found")} -> Sports | R14: {=XLOOKUP(E14,Store_Dim!A:A,Store_Dim!B:B,"Not Found")} -> South | S14: {=XLOOKUP(E14,Store_Dim!A:A,Store_Dim!D:D,"Not Found")} -> Online
A15: SALE13 | B15: 45493 | C15: CUST1443 | D15: PROD34 | E15: STORE16 | F15: 2 | G15: 316.9 | H15: 0.3 | I15: =F15*G15 -> 633.8 | J15: =H15*(1-I15) -> -189.84 | K15: =TEXT(B15,"mmm") -> Jul | L15: =YEAR(B15) -> 2024 | N15: {=XLOOKUP(C15,Customer_Dim!A:A,Customer_Dim!B:B,"Not Found")} -> Adam Castro | O15: {=XLOOKUP(C15,Customer_Dim!A:A,Customer_Dim!E:E,"Not Found")} -> New Donnabury | P15: {=XLOOKUP(D15,Product_Dim!A:A,Product_Dim!B:B,"Not Found")} -> Gaming Mechanical Keyboard | Q15: {=XLOOKUP(D15,Product_Dim!A:A,Product_Dim!C:C,"Not Found")} -> Electronics | R15: {=XLOOKUP(E15,Store_Dim!A:A,Store_Dim!B:B,"Not Found")} -> West | S15: {=XLOOKUP(E15,Store_Dim!A:A,Store_Dim!D:D,"Not Found")} -> Flagship
A16: SALE14 | B16: 45494 | C16: CUST1348 | D16: PROD24 | E16: STORE15 | F16: 4 | G16: 403.47 | H16: 0.29 | I16: =F16*G16 -> 1613.88 | J16: =H16*(1-I16) -> -467.7352 | K16: =TEXT(B16,"mmm") -> Jul | L16: =YEAR(B16) -> 2024 | N16: {=XLOOKUP(C16,Customer_Dim!A:A,Customer_Dim!B:B,"Not Found")} -> Sherry Cabrera | O16: {=XLOOKUP(C16,Customer_Dim!A:A,Customer_Dim!E:E,"Not Found")} -> Shannonview | P16: {=XLOOKUP(D16,Product_Dim!A:A,Product_Dim!B:B,"Not Found")} -> Foldable Camping Chair | Q16: {=XLOOKUP(D16,Product_Dim!A:A,Product_Dim!C:C,"Not Found")} -> Sports | R16: {=XLOOKUP(E16,Store_Dim!A:A,Store_Dim!B:B,"Not Found")} -> North | S16: {=XLOOKUP(E16,Store_Dim!A:A,Store_Dim!D:D,"Not Found")} -> Flagship
A17: SALE15 | B17: 45495 | C17: CUST1435 | D17: PROD36 | E17: STORE9 | G17: 871.34 | H17: 0.04 | I17: =F17*G17 -> 0 | J17: =H17*(1-I17) -> 0.04 | K17: =TEXT(B17,"mmm") -> Jul | L17: =YEAR(B17) -> 2024 | N17: {=XLOOKUP(C17,Customer_Dim!A:A,Customer_Dim!B:B,"Not Found")} -> Lindsay Beasley | O17: {=XLOOKUP(C17,Customer_Dim!A:A,Customer_Dim!E:E,"Not Found")} -> Wesleyhaven | P17: {=XLOOKUP(D17,Product_Dim!A:A,Product_Dim!B:B,"Not Found")} -> Women's Summer Dress | Q17: {=XLOOKUP(D17,Product_Dim!A:A,Product_Dim!C:C,"Not Found")} -> Clothing | R17: {=XLOOKUP(E17,Store_Dim!A:A,Store_Dim!B:B,"Not Found")} -> South | S17: {=XLOOKUP(E17,Store_Dim!A:A,Store_Dim!D:D,"Not Found")} -> Flagship
A18: SALE16 | B18: 45496 | C18: CUST1276 | D18: PROD65 | E18: STORE19 | F18: 2 | G18: 451.98 | H18: 0.25 | I18: =F18*G18 -> 903.96 | J18: =H18*(1-I18) -> -225.74 | K18: =TEXT(B18,"mmm") -> Jul | L18: =YEAR(B18) -> 2024 | N18: {=XLOOKUP(C18,Customer_Dim!A:A,Customer_Dim!B:B,"Not Found")} -> Arthur Warren | O18: {=XLOOKUP(C18,Customer_Dim!A:A,Customer_Dim!E:E,"Not Found")} -> Ericshire | P18: {=XLOOKUP(D18,Product_Dim!A:A,Product_Dim!B:B,"Not Found")} -> Adjustable Dumbbells 20kg | Q18: {=XLOOKUP(D18,Product_Dim!A:A,Product_Dim!C:C,"Not Found")} -> Sports | R18: {=XLOOKUP(E18,Store_Dim!A:A,Store_Dim!B:B,"Not Found")} -> East | S18: {=XLOOKUP(E18,Store_Dim!A:A,Store_Dim!D:D,"Not Found")} -> Online
A19: SALE17 | B19: 45497 | C19: CUST1079 | D19: PROD27 | E19: STORE4 | F19: 2 | G19: 502.69 | H19: 0.23 | I19: =F19*G19 -> 1005.38 | J19: =H19*(1-I19) -> -231.0074 | K19: =TEXT(B19,"mmm") -> Jul | L19: =YEAR(B19) -> 2024 | N19: {=XLOOKUP(C19,Customer_Dim!A:A,Customer_Dim!B:B,"Not Found")} -> Molly Gardner | O19: {=XLOOKUP(C19,Customer_Dim!A:A,Customer_Dim!E:E,"Not Found")} -> Nicoleborough | P19: {=XLOOKUP(D19,Product_Dim!A:A,Product_Dim!B:B,"Not Found")} -> Decorative Floor Vase | Q19: {=XLOOKUP(D19,Product_Dim!A:A,Product_Dim!C:C,"Not Found")} -> Home | R19: {=XLOOKUP(E19,Store_Dim!A:A,Store_Dim!B:B,"Not Found")} -> South | S19: {=XLOOKUP(E19,Store_Dim!A:A,Store_Dim!D:D,"Not Found")} -> Online
A20: SALE18 | B20: 45498 | C20: CUST1094 | D20: PROD39 | E20: STORE4 | F20: 2 | G20: 559.23 | H20: 0.25 | I20: =F20*G20 -> 1118.46 | J20: =H20*(1-I20) -> -279.365 | K20: =TEXT(B20,"mmm") -> Jul | L20: =YEAR(B20) -> 2024 | N20: {=XLOOKUP(C20,Customer_Dim!A:A,Customer_Dim!B:B,"Not Found")} -> David Patterson | O20: {=XLOOKUP(C20,Customer_Dim!A:A,Customer_Dim!E:E,"Not Found")} -> New Amyport | P20: {=XLOOKUP(D20,Product_Dim!A:A,Product_Dim!B:B,"Not Found")} -> Portable Power Bank | Q20: {=XLOOKUP(D20,Product_Dim!A:A,Product_Dim!C:C,"Not Found")} -> Electronics | R20: {=XLOOKUP(E20,Store_Dim!A:A,Store_Dim!B:B,"Not Found")} -> South | S20: {=XLOOKUP(E20,Store_Dim!A:A,Store_Dim!D:D,"Not Found")} -> Online
A21: SALE19 | B21: 45499 | C21: CUST1239 | D21: PROD60 | E21: STORE13 | F21: 4 | H21: 0.04 | I21: =F21*G21 -> 0 | J21: =H21*(1-I21) -> 0.04 | K21: =TEXT(B21,"mmm") -> Jul | L21: =YEAR(B21) -> 2024 | N21: {=XLOOKUP(C21,Customer_Dim!A:A,Customer_Dim!B:B,"Not Found")} -> Maria Hill | O21: {=XLOOKUP(C21,Customer_Dim!A:A,Customer_Dim!E:E,"Not Found")} -> Zamoraborough | P21: {=XLOOKUP(D21,Product_Dim!A:A,Product_Dim!B:B,"Not Found")} -> Luxury Perfume Spray | Q21: {=XLOOKUP(D21,Product_Dim!A:A,Product_Dim!C:C,"Not Found")} -> Beauty | R21: {=XLOOKUP(E21,Store_Dim!A:A,Store_Dim!B:B,"Not Found")} -> East | S21: {=XLOOKUP(E21,Store_Dim!A:A,Store_Dim!D:D,"Not Found")} -> Flagship
A22: SALE20 | B22: 45500 | C22: CUST1144 | D22: PROD72 | E22: STORE17 | F22: 3 | G22: 986.04 | H22: 0.27 | I22: =F22*G22 -> 2958.12 | J22: =H22*(1-I22) -> -798.4224 | K22: =TEXT(B22,"mmm") -> Jul | L22: =YEAR(B22) -> 2024 | N22: {=XLOOKUP(C22,Customer_Dim!A:A,Customer_Dim!B:B,"Not Found")} -> Justin Cross | O22: {=XLOOKUP(C22,Customer_Dim!A:A,Customer_Dim!E:E,"Not Found")} -> North Anthonychester | P22: {=XLOOKUP(D22,Product_Dim!A:A,Product_Dim!B:B,"Not Found")} -> Professional Jump Rope | Q22: {=XLOOKUP(D22,Product_Dim!A:A,Product_Dim!C:C,"Not Found")} -> Sports | R22: {=XLOOKUP(E22,Store_Dim!A:A,Store_Dim!B:B,"Not Found")} -> North | S22: {=XLOOKUP(E22,Store_Dim!A:A,Store_Dim!D:D,"Not Found")} -> Flagship
A23: SALE21 | B23: 45501 | C23: CUST1396 | D23: PROD43 | E23: STORE18 | F23: 1 | G23: 589.56 | H23: 0.22 | I23: =F23*G23 -> 589.56 | J23: =H23*(1-I23) -> -129.4832 | K23: =TEXT(B23,"mmm") -> Jul | L23: =YEAR(B23) -> 2024 | N23: {=XLOOKUP(C23,Customer_Dim!A:A,Customer_Dim!B:B,"Not Found")} -> Alexander Byrd | O23: {=XLOOKUP(C23,Customer_Dim!A:A,Customer_Dim!E:E,"Not Found")} -> Parkerview | P23: {=XLOOKUP(D23,Product_Dim!A:A,Product_Dim!B:B,"Not Found")} -> USB External Hard Drive | Q23: {=XLOOKUP(D23,Product_Dim!A:A,Product_Dim!C:C,"Not Found")} -> Electronics | R23: {=XLOOKUP(E23,Store_Dim!A:A,Store_Dim!B:B,"Not Found")} -> East | S23: {=XLOOKUP(E23,Store_Dim!A:A,Store_Dim!D:D,"Not Found")} -> Flagship
A24: SALE22 | B24: 45502 | C24: CUST1476 | D24: PROD69 | E24: STORE10 | F24: 3 | G24: 979.42 | H24: 0.03 | I24: =F24*G24 -> 2938.26 | J24: =H24*(1-I24) -> -88.1178 | K24: =TEXT(B24,"mmm") -> Jul | L24: =YEAR(B24) -> 2024 | N24: {=XLOOKUP(C24,Customer_Dim!A:A,Customer_Dim!B:B,"Not Found")} -> Elizabeth Foster | O24: {=XLOOKUP(C24,Customer_Dim!A:A,Customer_Dim!E:E,"Not Found")} -> Anthonymouth | P24: {=XLOOKUP(D24,Product_Dim!A:A,Product_Dim!B:B,"Not Found")} -> Men's Sports Shorts | Q24: {=XLOOKUP(D24,Product_Dim!A:A,Product_Dim!C:C,"Not Found")} -> Clothing | R24: {=XLOOKUP(E24,Store_Dim!A:A,Store_Dim!B:B,"Not Found")} -> East | S24: {=XLOOKUP(E24,Store_Dim!A:A,Store_Dim!D:D,"Not Found")} -> Online
A25: SALE23 | B25: 45503 | C25: CUST1368 | D25: PROD12 | E25: STORE8 | F25: 1 | G25: 719.28 | H25: 0.08 | I25: =F25*G25 -> 719.28 | J25: =H25*(1-I25) -> -57.4624 | K25: =TEXT(B25,"mmm") -> Jul | L25: =YEAR(B25) -> 2024 | N25: {=XLOOKUP(C25,Customer_Dim!A:A,Customer_Dim!B:B,"Not Found")} -> Miranda King | O25: {=XLOOKUP(C25,Customer_Dim!A:A,Customer_Dim!E:E,"Not Found")} -> West Mathew | P25: {=XLOOKUP(D25,Product_Dim!A:A,Product_Dim!B:B,"Not Found")} -> Hair Strengthening Shampoo | Q25: {=XLOOKUP(D25,Product_Dim!A:A,Product_Dim!C:C,"Not Found")} -> Beauty | R25: {=XLOOKUP(E25,Store_Dim!A:A,Store_Dim!B:B,"Not Found")} -> West | S25: {=XLOOKUP(E25,Store_Dim!A:A,Store_Dim!D:D,"Not Found")} -> Online
A26: SALE24 | B26: 45504 | C26: CUST1186 | D26: PROD67 | E26: STORE6 | F26: 3 | G26: 77.6 | H26: 0.07 | I26: =F26*G26 -> 232.8 | J26: =H26*(1-I26) -> -16.226 | K26: =TEXT(B26,"mmm") -> Jul | L26: =YEAR(B26) -> 2024 | N26: {=XLOOKUP(C26,Customer_Dim!A:A,Customer_Dim!B:B,"Not Found")} -> Jennifer Pruitt | O26: {=XLOOKUP(C26,Customer_Dim!A:A,Customer_Dim!E:E,"Not Found")} -> East Justin | P26: {=XLOOKUP(D26,Product_Dim!A:A,Product_Dim!B:B,"Not Found")} -> Smart LED Light Strip | Q26: {=XLOOKUP(D26,Product_Dim!A:A,Product_Dim!C:C,"Not Found")} -> Electronics | R26: {=XLOOKUP(E26,Store_Dim!A:A,Store_Dim!B:B,"Not Found")} -> East | S26: {=XLOOKUP(E26,Store_Dim!A:A,Store_Dim!D:D,"Not Found")} -> Online
A27: SALE25 | B27: 45505 | C27: CUST1381 | D27: PROD5 | E27: STORE3 | F27: 4 | G27: 852.71 | H27: 0.14 | I27: =F27*G27 -> 3410.84 | J27: =H27*(1-I27) -> -477.3776 | K27: =TEXT(B27,"mmm") -> Aug | L27: =YEAR(B27) -> 2024 | N27: {=XLOOKUP(C27,Customer_Dim!A:A,Customer_Dim!B:B,"Not Found")} -> Erika Padilla | O27: {=XLOOKUP(C27,Customer_Dim!A:A,Customer_Dim!E:E,"Not Found")} -> Andrewsland | P27: {=XLOOKUP(D27,Product_Dim!A:A,Product_Dim!B:B,"Not Found")} -> Men's Leather Belt | Q27: {=XLOOKUP(D27,Product_Dim!A:A,Product_Dim!C:C,"Not Found")} -> Clothing | R27: {=XLOOKUP(E27,Store_Dim!A:A,Store_Dim!B:B,"Not Found")} -> North | S27: {=XLOOKUP(E27,Store_Dim!A:A,Store_Dim!D:D,"Not Found")} -> Outlet
A28: SALE26 | B28: 45506 | C28: CUST1213 | D28: PROD98 | E28: STORE8 | F28: 4 | G28: 156.16 | I28: =F28*G28 -> 624.64 | J28: =H28*(1-I28) -> 0 | K28: =TEXT(B28,"mmm") -> Aug | L28: =YEAR(B28) -> 2024 | N28: {=XLOOKUP(C28,Customer_Dim!A:A,Customer_Dim!B:B,"Not Found")} -> Stuart Johnson | O28: {=XLOOKUP(C28,Customer_Dim!A:A,Customer_Dim!E:E,"Not Found")} -> West Markport | P28: {=XLOOKUP(D28,Product_Dim!A:A,Product_Dim!B:B,"Not Found")} -> Portable Bluetooth Speaker | Q28: {=XLOOKUP(D28,Product_Dim!A:A,Product_Dim!C:C,"Not Found")} -> Electronics | R28: {=XLOOKUP(E28,Store_Dim!A:A,Store_Dim!B:B,"Not Found")} -> West | S28: {=XLOOKUP(E28,Store_Dim!A:A,Store_Dim!D:D,"Not Found")} -> Online
A29: SALE27 | B29: 45507 | C29: CUST1200 | D29: PROD77 | E29: STORE8 | F29: 3 | G29: 815.49 | H29: 0.17 | I29: =F29*G29 -> 2446.47 | J29: =H29*(1-I29) -> -415.7299 | K29: =TEXT(B29,"mmm") -> Aug | L29: =YEAR(B29) -> 2024 | N29: {=XLOOKUP(C29,Customer_Dim!A:A,Customer_Dim!B:B,"Not Found")} -> Anna Perez | O29: {=XLOOKUP(C29,Customer_Dim!A:A,Customer_Dim!E:E,"Not Found")} -> South Jerry | P29: {=XLOOKUP(D29,Product_Dim!A:A,Product_Dim!B:B,"Not Found")} -> WiFi Mesh Router | Q29: {=XLOOKUP(D29,Product_Dim!A:A,Product_Dim!C:C,"Not Found")} -> Electronics | R29: {=XLOOKUP(E29,Store_Dim!A:A,Store_Dim!B:B,"Not Found")} -> West | S29: {=XLOOKUP(E29,Store_Dim!A:A,Store_Dim!D:D,"Not Found")} -> Online
A30: SALE28 | B30: 45508 | C30: CUST1148 | D30: PROD13 | E30: STORE2 | F30: 2 | G30: 74.21 | H30: 0.11 | I30: =F30*G30 -> 148.42 | J30: =H30*(1-I30) -> -16.2162 | K30: =TEXT(B30,"mmm") -> Aug | L30: =YEAR(B30) -> 2024 | N30: {=XLOOKUP(C30,Customer_Dim!A:A,Customer_Dim!B:B,"Not Found")} -> Theresa Campbell | O30: {=XLOOKUP(C30,Customer_Dim!A:A,Customer_Dim!E:E,"Not Found")} -> New Brian | P30: {=XLOOKUP(D30,Product_Dim!A:A,Product_Dim!B:B,"Not Found")} -> USB-C Fast Charger | Q30: {=XLOOKUP(D30,Product_Dim!A:A,Product_Dim!C:C,"Not Found")} -> Electronics | R30: {=XLOOKUP(E30,Store_Dim!A:A,Store_Dim!B:B,"Not Found")} -> South | S30: {=XLOOKUP(E30,Store_Dim!A:A,Store_Dim!D:D,"Not Found")} -> Outlet
A31: SALE29 | B31: 45509 | C31: CUST1348 | D31: PROD99 | E31: STORE3 | G31: 451.67 | H31: 0.15 | I31: =F31*G31 -> 0 | J31: =H31*(1-I31) -> 0.15 | K31: =TEXT(B31,"mmm") -> Aug | L31: =YEAR(B31) -> 2024 | N31: {=XLOOKUP(C31,Customer_Dim!A:A,Customer_Dim!B:B,"Not Found")} -> Sherry Cabrera | O31: {=XLOOKUP(C31,Customer_Dim!A:A,Customer_Dim!E:E,"Not Found")} -> Shannonview | P31: {=XLOOKUP(D31,Product_Dim!A:A,Product_Dim!B:B,"Not Found")} -> Stainless Steel Cookware Set | Q31: {=XLOOKUP(D31,Product_Dim!A:A,Product_Dim!C:C,"Not Found")} -> Home | R31: {=XLOOKUP(E31,Store_Dim!A:A,Store_Dim!B:B,"Not Found")} -> North | S31: {=XLOOKUP(E31,Store_Dim!A:A,Store_Dim!D:D,"Not Found")} -> Outlet
A32: SALE30 | B32: 45510 | C32: CUST1028 | D32: PROD5 | E32: STORE19 | F32: 1 | G32: 429.38 | H32: 0.13 | I32: =F32*G32 -> 429.38 | J32: =H32*(1-I32) -> -55.6894 | K32: =TEXT(B32,"mmm") -> Aug | L32: =YEAR(B32) -> 2024 | N32: {=XLOOKUP(C32,Customer_Dim!A:A,Customer_Dim!B:B,"Not Found")} -> Joshua Ryan | O32: {=XLOOKUP(C32,Customer_Dim!A:A,Customer_Dim!E:E,"Not Found")} -> New David | P32: {=XLOOKUP(D32,Product_Dim!A:A,Product_Dim!B:B,"Not Found")} -> Men's Leather Belt | Q32: {=XLOOKUP(D32,Product_Dim!A:A,Product_Dim!C:C,"Not Found")} -> Clothing | R32: {=XLOOKUP(E32,Store_Dim!A:A,Store_Dim!B:B,"Not Found")} -> East | S32: {=XLOOKUP(E32,Store_Dim!A:A,Store_Dim!D:D,"Not Found")} -> Online
A33: SALE31 | B33: 45511 | C33: CUST1412 | D33: PROD53 | E33: STORE12 | F33: 2 | G33: 148.96 | H33: 0.03 | I33: =F33*G33 -> 297.92 | J33: =H33*(1-I33) -> -8.9076 | K33: =TEXT(B33,"mmm") -> Aug | L33: =YEAR(B33) -> 2024 | N33: {=XLOOKUP(C33,Customer_Dim!A:A,Customer_Dim!B:B,"Not Found")} -> Shane Brown | O33: {=XLOOKUP(C33,Customer_Dim!A:A,Customer_Dim!E:E,"Not Found")} -> East Andrea | P33: {=XLOOKUP(D33,Product_Dim!A:A,Product_Dim!B:B,"Not Found")} -> Men's Track Pants | Q33: {=XLOOKUP(D33,Product_Dim!A:A,Product_Dim!C:C,"Not Found")} -> Clothing | R33: {=XLOOKUP(E33,Store_Dim!A:A,Store_Dim!B:B,"Not Found")} -> North | S33: {=XLOOKUP(E33,Store_Dim!A:A,Store_Dim!D:D,"Not Found")} -> Online
A34: SALE32 | B34: 45512 | C34: CUST1398 | D34: PROD75 | E34: STORE8 | F34: 4 | G34: 313.83 | H34: 0.08 | I34: =F34*G34 -> 1255.32 | J34: =H34*(1-I34) -> -100.3456 | K34: =TEXT(B34,"mmm") -> Aug | L34: =YEAR(B34) -> 2024 | N34: {=XLOOKUP(C34,Customer_Dim!A:A,Customer_Dim!B:B,"Not Found")} -> Jennifer Johnson | O34: {=XLOOKUP(C34,Customer_Dim!A:A,Customer_Dim!E:E,"Not Found")} -> Cheyenneborough | P34: {=XLOOKUP(D34,Product_Dim!A:A,Product_Dim!B:B,"Not Found")} -> Women's Ankle Boots | Q34: {=XLOOKUP(D34,Product_Dim!A:A,Product_Dim!C:C,"Not Found")} -> Clothing | R34: {=XLOOKUP(E34,Store_Dim!A:A,Store_Dim!B:B,"Not Found")} -> West | S34: {=XLOOKUP(E34,Store_Dim!A:A,Store_Dim!D:D,"Not Found")} -> Online
A35: SALE33 | B35: 45513 | C35: CUST1453 | D35: PROD12 | E35: STORE6 | F35: 2 | G35: 717.31 | H35: 0.15 | I35: =F35*G35 -> 1434.62 | J35: =H35*(1-I35) -> -215.043 | K35: =TEXT(B35,"mmm") -> Aug | L35: =YEAR(B35) -> 2024 | N35: {=XLOOKUP(C35,Customer_Dim!A:A,Customer_Dim!B:B,"Not Found")} -> April Phillips | O35: {=XLOOKUP(C35,Customer_Dim!A:A,Customer_Dim!E:E,"Not Found")} -> Lake Carolyn | P35: {=XLOOKUP(D35,Product_Dim!A:A,Product_Dim!B:B,"Not Found")} -> Hair Strengthening Shampoo | Q35: {=XLOOKUP(D35,Product_Dim!A:A,Product_Dim!C:C,"Not Found")} -> Beauty | R35: {=XLOOKUP(E35,Store_Dim!A:A,Store_Dim!B:B,"Not Found")} -> East | S35: {=XLOOKUP(E35,Store_Dim!A:A,Store_Dim!D:D,"Not Found")} -> Online
A36: SALE34 | B36: 45514 | C36: CUST1344 | D36: PROD79 | E36: STORE1 | G36: 873.22 | H36: 0.18 | I36: =F36*G36 -> 0 | J36: =H36*(1-I36) -> 0.18 | K36: =TEXT(B36,"mmm") -> Aug | L36: =YEAR(B36) -> 2024 | N36: {=XLOOKUP(C36,Customer_Dim!A:A,Customer_Dim!B:B,"Not Found")} -> Evelyn Brown | O36: {=XLOOKUP(C36,Customer_Dim!A:A,Customer_Dim!E:E,"Not Found")} -> West Victoriaborough | P36: {=XLOOKUP(D36,Product_Dim!A:A,Product_Dim!B:B,"Not Found")} -> Decorative Lamp Shade | Q36: {=XLOOKUP(D36,Product_Dim!A:A,Product_Dim!C:C,"Not Found")} -> Home | R36: {=XLOOKUP(E36,Store_Dim!A:A,Store_Dim!B:B,"Not Found")} -> North | S36: {=XLOOKUP(E36,Store_Dim!A:A,Store_Dim!D:D,"Not Found")} -> Flagship
A37: SALE35 | B37: 45515 | C37: CUST1218 | D37: PROD16 | E37: STORE3 | F37: 4 | G37: 109.36 | H37: 0.19 | I37: =F37*G37 -> 437.44 | J37: =H37*(1-I37) -> -82.9236 | K37: =TEXT(B37,"mmm") -> Aug | L37: =YEAR(B37) -> 2024 | N37: {=XLOOKUP(C37,Customer_Dim!A:A,Customer_Dim!B:B,"Not Found")} -> Julia Jackson | O37: {=XLOOKUP(C37,Customer_Dim!A:A,Customer_Dim!E:E,"Not Found")} -> Edwardland | P37: {=XLOOKUP(D37,Product_Dim!A:A,Product_Dim!B:B,"Not Found")} -> Not Found | Q37: {=XLOOKUP(D37,Product_Dim!A:A,Product_Dim!C:C,"Not Found")} -> Not Found | R37: {=XLOOKUP(E37,Store_Dim!A:A,Store_Dim!B:B,"Not Found")} -> North | S37: {=XLOOKUP(E37,Store_Dim!A:A,Store_Dim!D:D,"Not Found")} -> Outlet
A38: SALE36 | B38: 45516 | C38: CUST1086 | D38: PROD5 | E38: STORE7 | F38: 3 | G38: 559.52 | H38: 0.16 | I38: =F38*G38 -> 1678.56 | J38: =H38*(1-I38) -> -268.4096 | K38: =TEXT(B38,"mmm") -> Aug | L38: =YEAR(B38) -> 2024 | N38: {=XLOOKUP(C38,Customer_Dim!A:A,Customer_Dim!B:B,"Not Found")} -> Tammy Miller MD | O38: {=XLOOKUP(C38,Customer_Dim!A:A,Customer_Dim!E:E,"Not Found")} -> Austinfurt | P38: {=XLOOKUP(D38,Product_Dim!A:A,Product_Dim!B:B,"Not Found")} -> Men's Leather Belt | Q38: {=XLOOKUP(D38,Product_Dim!A:A,Product_Dim!C:C,"Not Found")} -> Clothing | R38: {=XLOOKUP(E38,Store_Dim!A:A,Store_Dim!B:B,"Not Found")} -> South | S38: {=XLOOKUP(E38,Store_Dim!A:A,Store_Dim!D:D,"Not Found")} -> Online
A39: SALE37 | B39: 45517 | C39: CUST1492 | D39: PROD10 | E39: STORE17 | F39: 3 | G39: 121.76 | H39: 0.27 | I39: =F39*G39 -> 365.28 | J39: =H39*(1-I39) -> -98.3556 | K39: =TEXT(B39,"mmm") -> Aug | L39: =YEAR(B39) -> 2024 | N39: {=XLOOKUP(C39,Customer_Dim!A:A,Customer_Dim!B:B,"Not Found")} -> Darrell Miller | O39: {=XLOOKUP(C39,Customer_Dim!A:A,Customer_Dim!E:E,"Not Found")} -> Port Carol | P39: {=XLOOKUP(D39,Product_Dim!A:A,Product_Dim!B:B,"Not Found")} -> Ceramic Kitchen Bowl Set | Q39: {=XLOOKUP(D39,Product_Dim!A:A,Product_Dim!C:C,"Not Found")} -> Home | R39: {=XLOOKUP(E39,Store_Dim!A:A,Store_Dim!B:B,"Not Found")} -> North | S39: {=XLOOKUP(E39,Store_Dim!A:A,Store_Dim!D:D,"Not Found")} -> Flagship
A40: SALE38 | B40: 45518 | C40: CUST1189 | D40: PROD33 | E40: STORE13 | F40: 4 | G40: 735.32 | H40: 0.06 | I40: =F40*G40 -> 2941.28 | J40: =H40*(1-I40) -> -176.4168 | K40: =TEXT(B40,"mmm") -> Aug | L40: =YEAR(B40) -> 2024 | N40: {=XLOOKUP(C40,Customer_Dim!A:A,Customer_Dim!B:B,"Not Found")} -> Daniel Austin | O40: {=XLOOKUP(C40,Customer_Dim!A:A,Customer_Dim!E:E,"Not Found")} -> Lake Howardberg | P40: {=XLOOKUP(D40,Product_Dim!A:A,Product_Dim!B:B,"Not Found")} -> Modern Wall Clock | Q40: {=XLOOKUP(D40,Product_Dim!A:A,Product_Dim!C:C,"Not Found")} -> Home | R40: {=XLOOKUP(E40,Store_Dim!A:A,Store_Dim!B:B,"Not Found")} -> East | S40: {=XLOOKUP(E40,Store_Dim!A:A,Store_Dim!D:D,"Not Found")} -> Flagship
A41: SALE39 | B41: 45519 | C41: CUST1431 | D41: PROD94 | E41: STORE3 | F41: 2 | G41: 600.73 | H41: 0.08 | I41: =F41*G41 -> 1201.46 | J41: =H41*(1-I41) -> -96.0368 | K41: =TEXT(B41,"mmm") -> Aug | L41: =YEAR(B41) -> 2024 | N41: {=XLOOKUP(C41,Customer_Dim!A:A,Customer_Dim!B:B,"Not Found")} -> John Smith | O41: {=XLOOKUP(C41,Customer_Dim!A:A,Customer_Dim!E:E,"Not Found")} -> South Andrewport | P41: {=XLOOKUP(D41,Product_Dim!A:A,Product_Dim!B:B,"Not Found")} -> Vitamin E Body Lotion | Q41: {=XLOOKUP(D41,Product_Dim!A:A,Product_Dim!C:C,"Not Found")} -> Beauty | R41: {=XLOOKUP(E41,Store_Dim!A:A,Store_Dim!B:B,"Not Found")} -> North | S41: {=XLOOKUP(E41,Store_Dim!A:A,Store_Dim!D:D,"Not Found")} -> Outlet
A42: SALE40 | B42: 45520 | C42: CUST1072 | D42: PROD26 | E42: STORE19 | F42: 2 | G42: 873.86 | H42: 0.07 | I42: =F42*G42 -> 1747.72 | J42: =H42*(1-I42) -> -122.2704 | K42: =TEXT(B42,"mmm") -> Aug | L42: =YEAR(B42) -> 2024 | N42: {=XLOOKUP(C42,Customer_Dim!A:A,Customer_Dim!B:B,"Not Found")} -> Tonya Burch | O42: {=XLOOKUP(C42,Customer_Dim!A:A,Customer_Dim!E:E,"Not Found")} -> Olsonhaven | P42: {=XLOOKUP(D42,Product_Dim!A:A,Product_Dim!B:B,"Not Found")} -> Wireless Bluetooth Speaker | Q42: {=XLOOKUP(D42,Product_Dim!A:A,Product_Dim!C:C,"Not Found")} -> Electronics | R42: {=XLOOKUP(E42,Store_Dim!A:A,Store_Dim!B:B,"Not Found")} -> East | S42: {=XLOOKUP(E42,Store_Dim!A:A,Store_Dim!D:D,"Not Found")} -> Online
A43: SALE41 | B43: 45521 | C43: CUST1302 | D43: PROD23 | E43: STORE8 | F43: 3 | G43: 342.47 | H43: 0.08 | I43: =F43*G43 -> 1027.41 | J43: =H43*(1-I43) -> -82.1128 | K43: =TEXT(B43,"mmm") -> Aug | L43: =YEAR(B43) -> 2024 | N43: {=XLOOKUP(C43,Customer_Dim!A:A,Customer_Dim!B:B,"Not Found")} -> Edward Cole | O43: {=XLOOKUP(C43,Customer_Dim!A:A,Customer_Dim!E:E,"Not Found")} -> Lake Charlotte | P43: {=XLOOKUP(D43,Product_Dim!A:A,Product_Dim!B:B,"Not Found")} -> Men's Formal Shirt | Q43: {=XLOOKUP(D43,Product_Dim!A:A,Product_Dim!C:C,"Not Found")} -> Clothing | R43: {=XLOOKUP(E43,Store_Dim!A:A,Store_Dim!B:B,"Not Found")} -> West | S43: {=XLOOKUP(E43,Store_Dim!A:A,Store_Dim!D:D,"Not Found")} -> Online
A44: SALE42 | B44: 45522 | C44: CUST1335 | D44: PROD29 | E44: STORE9 | F44: 2 | G44: 915.15 | H44: 0.16 | I44: =F44*G44 -> 1830.3 | J44: =H44*(1-I44) -> -292.688 | K44: =TEXT(B44,"mmm") -> Aug | L44: =YEAR(B44) -> 2024 | N44: {=XLOOKUP(C44,Customer_Dim!A:A,Customer_Dim!B:B,"Not Found")} -> Jennifer Woods | O44: {=XLOOKUP(C44,Customer_Dim!A:A,Customer_Dim!E:E,"Not Found")} -> West Brendamouth | P44: {=XLOOKUP(D44,Product_Dim!A:A,Product_Dim!B:B,"Not Found")} -> Fabric Sofa Throw Blanket | Q44: {=XLOOKUP(D44,Product_Dim!A:A,Product_Dim!C:C,"Not Found")} -> Home | R44: {=XLOOKUP(E44,Store_Dim!A:A,Store_Dim!B:B,"Not Found")} -> South | S44: {=XLOOKUP(E44,Store_Dim!A:A,Store_Dim!D:D,"Not Found")} -> Flagship
A45: SALE43 | B45: 45523 | C45: CUST1084 | D45: PROD33 | E45: STORE17 | G45: 863.11 | H45: 0.28 | I45: =F45*G45 -> 0 | J45: =H45*(1-I45) -> 0.28 | K45: =TEXT(B45,"mmm") -> Aug | L45: =YEAR(B45) -> 2024 | N45: {=XLOOKUP(C45,Customer_Dim!A:A,Customer_Dim!B:B,"Not Found")} -> Christy Hoffman | O45: {=XLOOKUP(C45,Customer_Dim!A:A,Customer_Dim!E:E,"Not Found")} -> Garyberg | P45: {=XLOOKUP(D45,Product_Dim!A:A,Product_Dim!B:B,"Not Found")} -> Modern Wall Clock | Q45: {=XLOOKUP(D45,Product_Dim!A:A,Product_Dim!C:C,"Not Found")} -> Home | R45: {=XLOOKUP(E45,Store_Dim!A:A,Store_Dim!B:B,"Not Found")} -> North | S45: {=XLOOKUP(E45,Store_Dim!A:A,Store_Dim!D:D,"Not Found")} -> Flagship
A46: SALE44 | B46: 45524 | C46: CUST1203 | D46: PROD43 | E46: STORE12 | F46: 2 | G46: 209.32 | H46: 0.23 | I46: =F46*G46 -> 418.64 | J46: =H46*(1-I46) -> -96.0572 | K46: =TEXT(B46,"mmm") -> Aug | L46: =YEAR(B46) -> 2024 | N46: {=XLOOKUP(C46,Customer_Dim!A:A,Customer_Dim!B:B,"Not Found")} -> Sarah Brady | O46: {=XLOOKUP(C46,Customer_Dim!A:A,Customer_Dim!E:E,"Not Found")} -> Johnsonland | P46: {=XLOOKUP(D46,Product_Dim!A:A,Product_Dim!B:B,"Not Found")} -> USB External Hard Drive | Q46: {=XLOOKUP(D46,Product_Dim!A:A,Product_Dim!C:C,"Not Found")} -> Electronics | R46: {=XLOOKUP(E46,Store_Dim!A:A,Store_Dim!B:B,"Not Found")} -> North | S46: {=XLOOKUP(E46,Store_Dim!A:A,Store_Dim!D:D,"Not Found")} -> Online
A47: SALE45 | B47: 45525 | C47: CUST1470 | D47: PROD59 | E47: STORE8 | F47: 4 | G47: 288.6 | H47: 0.09 | I47: =F47*G47 -> 1154.4 | J47: =H47*(1-I47) -> -103.806 | K47: =TEXT(B47,"mmm") -> Aug | L47: =YEAR(B47) -> 2024 | N47: {=XLOOKUP(C47,Customer_Dim!A:A,Customer_Dim!B:B,"Not Found")} -> Manuel Fisher | O47: {=XLOOKUP(C47,Customer_Dim!A:A,Customer_Dim!E:E,"Not Found")} -> Kanebury | P47: {=XLOOKUP(D47,Product_Dim!A:A,Product_Dim!B:B,"Not Found")} -> Men's Hair Styling Gel | Q47: {=XLOOKUP(D47,Product_Dim!A:A,Product_Dim!C:C,"Not Found")} -> Beauty | R47: {=XLOOKUP(E47,Store_Dim!A:A,Store_Dim!B:B,"Not Found")} -> West | S47: {=XLOOKUP(E47,Store_Dim!A:A,Store_Dim!D:D,"Not Found")} -> Online
A48: SALE46 | B48: 45526 | C48: CUST1070 | D48: PROD78 | E48: STORE16 | F48: 1 | G48: 418.69 | H48: 0.06 | I48: =F48*G48 -> 418.69 | J48: =H48*(1-I48) -> -25.0614 | K48: =TEXT(B48,"mmm") -> Aug | L48: =YEAR(B48) -> 2024 | N48: {=XLOOKUP(C48,Customer_Dim!A:A,Customer_Dim!B:B,"Not Found")} -> Eric Singh | O48: {=XLOOKUP(C48,Customer_Dim!A:A,Customer_Dim!E:E,"Not Found")} -> Port Lisa | P48: {=XLOOKUP(D48,Product_Dim!A:A,Product_Dim!B:B,"Not Found")} -> Essential Oil Diffuser | Q48: {=XLOOKUP(D48,Product_Dim!A:A,Product_Dim!C:C,"Not Found")} -> Home | R48: {=XLOOKUP(E48,Store_Dim!A:A,Store_Dim!B:B,"Not Found")} -> West | S48: {=XLOOKUP(E48,Store_Dim!A:A,Store_Dim!D:D,"Not Found")} -> Flagship
A49: SALE47 | B49: 45527 | C49: CUST1008 | D49: PROD30 | E49: STORE11 | F49: 1 | G49: 135.78 | H49: 0.14 | I49: =F49*G49 -> 135.78 | J49: =H49*(1-I49) -> -18.8692 | K49: =TEXT(B49,"mmm") -> Aug | L49: =YEAR(B49) -> 2024 | N49: {=XLOOKUP(C49,Customer_Dim!A:A,Customer_Dim!B:B,"Not Found")} -> Melissa Howard | O49: {=XLOOKUP(C49,Customer_Dim!A:A,Customer_Dim!E:E,"Not Found")} -> Maynardton | P49: {=XLOOKUP(D49,Product_Dim!A:A,Product_Dim!B:B,"Not Found")} -> Stainless Steel Cutlery Set | Q49: {=XLOOKUP(D49,Product_Dim!A:A,Product_Dim!C:C,"Not Found")} -> Home | R49: {=XLOOKUP(E49,Store_Dim!A:A,Store_Dim!B:B,"Not Found")} -> South | S49: {=XLOOKUP(E49,Store_Dim!A:A,Store_Dim!D:D,"Not Found")} -> Online
A50: SALE48 | B50: 45528 | C50: CUST1203 | D50: PROD44 | E50: STORE17 | F50: 1 | G50: 517.13 | H50: 0.28 | I50: =F50*G50 -> 517.13 | J50: =H50*(1-I50) -> -144.5164 | K50: =TEXT(B50,"mmm") -> Aug | L50: =YEAR(B50) -> 2024 | N50: {=XLOOKUP(C50,Customer_Dim!A:A,Customer_Dim!B:B,"Not Found")} -> Sarah Brady | O50: {=XLOOKUP(C50,Customer_Dim!A:A,Customer_Dim!E:E,"Not Found")} -> Johnsonland | P50: {=XLOOKUP(D50,Product_Dim!A:A,Product_Dim!B:B,"Not Found")} -> Adjustable Jump Rope | Q50: {=XLOOKUP(D50,Product_Dim!A:A,Product_Dim!C:C,"Not Found")} -> Sports | R50: {=XLOOKUP(E50,Store_Dim!A:A,Store_Dim!B:B,"Not Found")} -> North | S50: {=XLOOKUP(E50,Store_Dim!A:A,Store_Dim!D:D,"Not Found")} -> Flagship
A51: SALE49 | B51: 45529 | C51: CUST1420 | D51: PROD21 | E51: STORE16 | F51: 2 | G51: 384.66 | H51: 0.08 | I51: =F51*G51 -> 769.32 | J51: =H51*(1-I51) -> -61.4656 | K51: =TEXT(B51,"mmm") -> Aug | L51: =YEAR(B51) -> 2024 | N51: {=XLOOKUP(C51,Customer_Dim!A:A,Customer_Dim!B:B,"Not Found")} -> Dr. Tamara White MD | O51: {=XLOOKUP(C51,Customer_Dim!A:A,Customer_Dim!E:E,"Not Found")} -> New Benjamin | P51: {=XLOOKUP(D51,Product_Dim!A:A,Product_Dim!B:B,"Not Found")} -> Multi-Purpose Storage Box | Q51: {=XLOOKUP(D51,Product_Dim!A:A,Product_Dim!C:C,"Not Found")} -> Home | R51: {=XLOOKUP(E51,Store_Dim!A:A,Store_Dim!B:B,"Not Found")} -> West | S51: {=XLOOKUP(E51,Store_Dim!A:A,Store_Dim!D:D,"Not Found")} -> Flagship
A52: SALE50 | B52: 45530 | C52: CUST1070 | D52: PROD52 | E52: STORE9 | F52: 3 | G52: 83.7 | H52: 0.24 | I52: =F52*G52 -> 251.1 | J52: =H52*(1-I52) -> -60.024 | K52: =TEXT(B52,"mmm") -> Aug | L52: =YEAR(B52) -> 2024 | N52: {=XLOOKUP(C52,Customer_Dim!A:A,Customer_Dim!B:B,"Not Found")} -> Eric Singh | O52: {=XLOOKUP(C52,Customer_Dim!A:A,Customer_Dim!E:E,"Not Found")} -> Port Lisa | P52: {=XLOOKUP(D52,Product_Dim!A:A,Product_Dim!B:B,"Not Found")} -> Rugby Ball | Q52: {=XLOOKUP(D52,Product_Dim!A:A,Product_Dim!C:C,"Not Found")} -> Sports | R52: {=XLOOKUP(E52,Store_Dim!A:A,Store_Dim!B:B,"Not Found")} -> South | S52: {=XLOOKUP(E52,Store_Dim!A:A,Store_Dim!D:D,"Not Found")} -> Flagship
A53: SALE51 | B53: 45531 | C53: CUST1142 | D53: PROD69 | E53: STORE7 | F53: 3 | G53: 76.57 | H53: 0.26 | I53: =F53*G53 -> 229.71 | J53: =H53*(1-I53) -> -59.4646 | K53: =TEXT(B53,"mmm") -> Aug | L53: =YEAR(B53) -> 2024 | N53: {=XLOOKUP(C53,Customer_Dim!A:A,Customer_Dim!B:B,"Not Found")} -> Maria Ramirez | O53: {=XLOOKUP(C53,Customer_Dim!A:A,Customer_Dim!E:E,"Not Found")} -> West Brandon | P53: {=XLOOKUP(D53,Product_Dim!A:A,Product_Dim!B:B,"Not Found")} -> Men's Sports Shorts | Q53: {=XLOOKUP(D53,Product_Dim!A:A,Product_Dim!C:C,"Not Found")} -> Clothing | R53: {=XLOOKUP(E53,Store_Dim!A:A,Store_Dim!B:B,"Not Found")} -> South | S53: {=XLOOKUP(E53,Store_Dim!A:A,Store_Dim!D:D,"Not Found")} -> Online
A54: SALE52 | B54: 45532 | C54: CUST1148 | D54: PROD89 | E54: STORE6 | F54: 3 | I54: =F54*G54 -> 0 | J54: =H54*(1-I54) -> 0 | K54: =TEXT(B54,"mmm") -> Aug | L54: =YEAR(B54) -> 2024 | N54: {=XLOOKUP(C54,Customer_Dim!A:A,Customer_Dim!B:B,"Not Found")} -> Theresa Campbell | O54: {=XLOOKUP(C54,Customer_Dim!A:A,Customer_Dim!E:E,"Not Found")} -> New Brian | P54: {=XLOOKUP(D54,Product_Dim!A:A,Product_Dim!B:B,"Not Found")} -> Face Foundation Kit | Q54: {=XLOOKUP(D54,Product_Dim!A:A,Product_Dim!C:C,"Not Found")} -> Beauty | R54: {=XLOOKUP(E54,Store_Dim!A:A,Store_Dim!B:B,"Not Found")} -> East | S54: {=XLOOKUP(E54,Store_Dim!A:A,Store_Dim!D:D,"Not Found")} -> Online
A55: SALE53 | B55: 45533 | C55: CUST1324 | D55: PROD20 | E55: STORE8 | F55: 1 | G55: 900.35 | H55: 0.13 | I55: =F55*G55 -> 900.35 | J55: =H55*(1-I55) -> -116.9155 | K55: =TEXT(B55,"mmm") -> Aug | L55: =YEAR(B55) -> 2024 | N55: {=XLOOKUP(C55,Customer_Dim!A:A,Customer_Dim!B:B,"Not Found")} -> Alex Mann II | O55: {=XLOOKUP(C55,Customer_Dim!A:A,Customer_Dim!E:E,"Not Found")} -> South Zacharychester | P55: {=XLOOKUP(D55,Product_Dim!A:A,Product_Dim!B:B,"Not Found")} -> Outdoor Sports Water Bottle | Q55: {=XLOOKUP(D55,Product_Dim!A:A,Product_Dim!C:C,"Not Found")} -> Sports | R55: {=XLOOKUP(E55,Store_Dim!A:A,Store_Dim!B:B,"Not Found")} -> West | S55: {=XLOOKUP(E55,Store_Dim!A:A,Store_Dim!D:D,"Not Found")} -> Online
A56: SALE54 | B56: 45534 | C56: CUST1095 | D56: PROD40 | E56: STORE10 | F56: 4 | G56: 428.09 | H56: 0.07 | I56: =F56*G56 -> 1712.36 | J56: =H56*(1-I56) -> -119.7952 | K56: =TEXT(B56,"mmm") -> Aug | L56: =YEAR(B56) -> 2024 | N56: {=XLOOKUP(C56,Customer_Dim!A:A,Customer_Dim!B:B,"Not Found")} -> Amy Fowler | O56: {=XLOOKUP(C56,Customer_Dim!A:A,Customer_Dim!E:E,"Not Found")} -> West Bobbyshire | P56: {=XLOOKUP(D56,Product_Dim!A:A,Product_Dim!B:B,"Not Found")} -> Noise-Canceling Headphones | Q56: {=XLOOKUP(D56,Product_Dim!A:A,Product_Dim!C:C,"Not Found")} -> Electronics | R56: {=XLOOKUP(E56,Store_Dim!A:A,Store_Dim!B:B,"Not Found")} -> East | S56: {=XLOOKUP(E56,Store_Dim!A:A,Store_Dim!D:D,"Not Found")} -> Online
A57: SALE55 | B57: 45535 | C57: CUST1416 | D57: PROD49 | E57: STORE11 | F57: 2 | G57: 559.71 | H57: 0.3 | I57: =F57*G57 -> 1119.42 | J57: =H57*(1-I57) -> -335.526 | K57: =TEXT(B57,"mmm") -> Aug | L57: =YEAR(B57) -> 2024 | N57: {=XLOOKUP(C57,Customer_Dim!A:A,Customer_Dim!B:B,"Not Found")} -> Jennifer Myers | O57: {=XLOOKUP(C57,Customer_Dim!A:A,Customer_Dim!E:E,"Not Found")} -> Marthaborough | P57: {=XLOOKUP(D57,Product_Dim!A:A,Product_Dim!B:B,"Not Found")} -> Men's Roll-On Perfume | Q57: {=XLOOKUP(D57,Product_Dim!A:A,Product_Dim!C:C,"Not Found")} -> Beauty | R57: {=XLOOKUP(E57,Store_Dim!A:A,Store_Dim!B:B,"Not Found")} -> South | S57: {=XLOOKUP(E57,Store_Dim!A:A,Store_Dim!D:D,"Not Found")} -> Online
A58: SALE56 | B58: 45536 | C58: CUST1080 | D58: PROD34 | E58: STORE6 | F58: 2 | G58: 833.7 | H58: 0.06 | I58: =F58*G58 -> 1667.4 | J58: =H58*(1-I58) -> -99.984 | K58: =TEXT(B58,"mmm") -> Sep | L58: =YEAR(B58) -> 2024 | N58: {=XLOOKUP(C58,Customer_Dim!A:A,Customer_Dim!B:B,"Not Found")} -> Jennifer Garcia | O58: {=XLOOKUP(C58,Customer_Dim!A:A,Customer_Dim!E:E,"Not Found")} -> New Sean | P58: {=XLOOKUP(D58,Product_Dim!A:A,Product_Dim!B:B,"Not Found")} -> Gaming Mechanical Keyboard | Q58: {=XLOOKUP(D58,Product_Dim!A:A,Product_Dim!C:C,"Not Found")} -> Electronics | R58: {=XLOOKUP(E58,Store_Dim!A:A,Store_Dim!B:B,"Not Found")} -> East | S58: {=XLOOKUP(E58,Store_Dim!A:A,Store_Dim!D:D,"Not Found")} -> Online
A59: SALE57 | B59: 45537 | C59: CUST1467 | D59: PROD47 | E59: STORE14 | F59: 2 | G59: 680.16 | H59: 0.28 | I59: =F59*G59 -> 1360.32 | J59: =H59*(1-I59) -> -380.6096 | K59: =TEXT(B59,"mmm") -> Sep | L59: =YEAR(B59) -> 2024 | N59: {=XLOOKUP(C59,Customer_Dim!A:A,Customer_Dim!B:B,"Not Found")} -> Michael Foley | O59: {=XLOOKUP(C59,Customer_Dim!A:A,Customer_Dim!E:E,"Not Found")} -> Oneillfurt | P59: {=XLOOKUP(D59,Product_Dim!A:A,Product_Dim!B:B,"Not Found")} -> Makeup Brush Set | Q59: {=XLOOKUP(D59,Product_Dim!A:A,Product_Dim!C:C,"Not Found")} -> Beauty | R59: {=XLOOKUP(E59,Store_Dim!A:A,Store_Dim!B:B,"Not Found")} -> South | S59: {=XLOOKUP(E59,Store_Dim!A:A,Store_Dim!D:D,"Not Found")} -> Outlet
A60: SALE58 | B60: 45538 | C60: CUST1404 | D60: PROD15 | E60: STORE7 | F60: 4 | G60: 733.42 | I60: =F60*G60 -> 2933.68 | J60: =H60*(1-I60) -> 0 | K60: =TEXT(B60,"mmm") -> Sep | L60: =YEAR(B60) -> 2024 | N60: {=XLOOKUP(C60,Customer_Dim!A:A,Customer_Dim!B:B,"Not Found")} -> David Ross | O60: {=XLOOKUP(C60,Customer_Dim!A:A,Customer_Dim!E:E,"Not Found")} -> South Angela | P60: {=XLOOKUP(D60,Product_Dim!A:A,Product_Dim!B:B,"Not Found")} -> 4K Home Projector | Q60: {=XLOOKUP(D60,Product_Dim!A:A,Product_Dim!C:C,"Not Found")} -> Electronics | R60: {=XLOOKUP(E60,Store_Dim!A:A,Store_Dim!B:B,"Not Found")} -> South | S60: {=XLOOKUP(E60,Store_Dim!A:A,Store_Dim!D:D,"Not Found")} -> Online
A61: SALE59 | B61: 45539 | C61: CUST1367 | D61: PROD89 | E61: STORE11 | F61: 1 | G61: 996.33 | H61: 0.23 | I61: =F61*G61 -> 996.33 | J61: =H61*(1-I61) -> -228.9259 | K61: =TEXT(B61,"mmm") -> Sep | L61: =YEAR(B61) -> 2024 | N61: {=XLOOKUP(C61,Customer_Dim!A:A,Customer_Dim!B:B,"Not Found")} -> Melinda Johnson | O61: {=XLOOKUP(C61,Customer_Dim!A:A,Customer_Dim!E:E,"Not Found")} -> Kaufmanfurt | P61: {=XLOOKUP(D61,Product_Dim!A:A,Product_Dim!B:B,"Not Found")} -> Face Foundation Kit | Q61: {=XLOOKUP(D61,Product_Dim!A:A,Product_Dim!C:C,"Not Found")} -> Beauty | R61: {=XLOOKUP(E61,Store_Dim!A:A,Store_Dim!B:B,"Not Found")} -> South | S61: {=XLOOKUP(E61,Store_Dim!A:A,Store_Dim!D:D,"Not Found")} -> Online
A62: SALE60 | B62: 45540 | C62: CUST1408 | D62: PROD31 | E62: STORE10 | F62: 1 | G62: 198.83 | H62: 0.09 | I62: =F62*G62 -> 198.83 | J62: =H62*(1-I62) -> -17.8047 | K62: =TEXT(B62,"mmm") -> Sep | L62: =YEAR(B62) -> 2024 | N62: {=XLOOKUP(C62,Customer_Dim!A:A,Customer_Dim!B:B,"Not Found")} -> Isabel Foster | O62: {=XLOOKUP(C62,Customer_Dim!A:A,Customer_Dim!E:E,"Not Found")} -> Port Joshuaville | P62: {=XLOOKUP(D62,Product_Dim!A:A,Product_Dim!B:B,"Not Found")} -> Basketball | Q62: {=XLOOKUP(D62,Product_Dim!A:A,Product_Dim!C:C,"Not Found")} -> Sports | R62: {=XLOOKUP(E62,Store_Dim!A:A,Store_Dim!B:B,"Not Found")} -> East | S62: {=XLOOKUP(E62,Store_Dim!A:A,Store_Dim!D:D,"Not Found")} -> Online
A63: SALE61 | B63: 45541 | C63: CUST1239 | D63: PROD19 | E63: STORE7 | F63: 1 | G63: 374.92 | H63: 0.18 | I63: =F63*G63 -> 374.92 | J63: =H63*(1-I63) -> -67.3056 | K63: =TEXT(B63,"mmm") -> Sep | L63: =YEAR(B63) -> 2024 | N63: {=XLOOKUP(C63,Customer_Dim!A:A,Customer_Dim!B:B,"Not Found")} -> Maria Hill | O63: {=XLOOKUP(C63,Customer_Dim!A:A,Customer_Dim!E:E,"Not Found")} -> Zamoraborough | P63: {=XLOOKUP(D63,Product_Dim!A:A,Product_Dim!B:B,"Not Found")} -> Knee Support Brace | Q63: {=XLOOKUP(D63,Product_Dim!A:A,Product_Dim!C:C,"Not Found")} -> Sports | R63: {=XLOOKUP(E63,Store_Dim!A:A,Store_Dim!B:B,"Not Found")} -> South | S63: {=XLOOKUP(E63,Store_Dim!A:A,Store_Dim!D:D,"Not Found")} -> Online
A64: SALE62 | B64: 45542 | C64: CUST1464 | D64: PROD93 | E64: STORE16 | F64: 1 | G64: 468.94 | H64: 0.12 | I64: =F64*G64 -> 468.94 | J64: =H64*(1-I64) -> -56.1528 | K64: =TEXT(B64,"mmm") -> Sep | L64: =YEAR(B64) -> 2024 | N64: {=XLOOKUP(C64,Customer_Dim!A:A,Customer_Dim!B:B,"Not Found")} -> David Pierce | O64: {=XLOOKUP(C64,Customer_Dim!A:A,Customer_Dim!E:E,"Not Found")} -> Grayland | P64: {=XLOOKUP(D64,Product_Dim!A:A,Product_Dim!B:B,"Not Found")} -> USB-C Laptop Charger | Q64: {=XLOOKUP(D64,Product_Dim!A:A,Product_Dim!C:C,"Not Found")} -> Electronics | R64: {=XLOOKUP(E64,Store_Dim!A:A,Store_Dim!B:B,"Not Found")} -> West | S64: {=XLOOKUP(E64,Store_Dim!A:A,Store_Dim!D:D,"Not Found")} -> Flagship
A65: SALE63 | B65: 45543 | C65: CUST1126 | D65: PROD89 | E65: STORE12 | F65: 2 | G65: 121.37 | H65: 0.05 | I65: =F65*G65 -> 242.74 | J65: =H65*(1-I65) -> -12.087 | K65: =TEXT(B65,"mmm") -> Sep | L65: =YEAR(B65) -> 2024 | N65: {=XLOOKUP(C65,Customer_Dim!A:A,Customer_Dim!B:B,"Not Found")} -> James Wolfe | O65: {=XLOOKUP(C65,Customer_Dim!A:A,Customer_Dim!E:E,"Not Found")} -> Benjaminton | P65: {=XLOOKUP(D65,Product_Dim!A:A,Product_Dim!B:B,"Not Found")} -> Face Foundation Kit | Q65: {=XLOOKUP(D65,Product_Dim!A:A,Product_Dim!C:C,"Not Found")} -> Beauty | R65: {=XLOOKUP(E65,Store_Dim!A:A,Store_Dim!B:B,"Not Found")} -> North | S65: {=XLOOKUP(E65,Store_Dim!A:A,Store_Dim!D:D,"Not Found")} -> Online
A66: SALE64 | B66: 45544 | C66: CUST1255 | D66: PROD53 | E66: STORE10 | F66: 3 | G66: 480.06 | H66: 0.01 | I66: =F66*G66 -> 1440.18 | J66: =H66*(1-I66) -> -14.3918 | K66: =TEXT(B66,"mmm") -> Sep | L66: =YEAR(B66) -> 2024 | N66: {=XLOOKUP(C66,Customer_Dim!A:A,Customer_Dim!B:B,"Not Found")} -> Damon Perez | O66: {=XLOOKUP(C66,Customer_Dim!A:A,Customer_Dim!E:E,"Not Found")} -> Jasonton | P66: {=XLOOKUP(D66,Product_Dim!A:A,Product_Dim!B:B,"Not Found")} -> Men's Track Pants | Q66: {=XLOOKUP(D66,Product_Dim!A:A,Product_Dim!C:C,"Not Found")} -> Clothing | R66: {=XLOOKUP(E66,Store_Dim!A:A,Store_Dim!B:B,"Not Found")} -> East | S66: {=XLOOKUP(E66,Store_Dim!A:A,Store_Dim!D:D,"Not Found")} -> Online
A67: SALE65 | B67: 45545 | C67: CUST1162 | D67: PROD99 | E67: STORE17 | F67: 2 | G67: 856.57 | H67: 0.24 | I67: =F67*G67 -> 1713.14 | J67: =H67*(1-I67) -> -410.9136 | K67: =TEXT(B67,"mmm") -> Sep | L67: =YEAR(B67) -> 2024 | N67: {=XLOOKUP(C67,Customer_Dim!A:A,Customer_Dim!B:B,"Not Found")} -> Mariah Brown | O67: {=XLOOKUP(C67,Customer_Dim!A:A,Customer_Dim!E:E,"Not Found")} -> Palmerbury | P67: {=XLOOKUP(D67,Product_Dim!A:A,Product_Dim!B:B,"Not Found")} -> Stainless Steel Cookware Set | Q67: {=XLOOKUP(D67,Product_Dim!A:A,Product_Dim!C:C,"Not Found")} -> Home | R67: {=XLOOKUP(E67,Store_Dim!A:A,Store_Dim!B:B,"Not Found")} -> North | S67: {=XLOOKUP(E67,Store_Dim!A:A,Store_Dim!D:D,"Not Found")} -> Flagship
A68: SALE66 | B68: 45546 | C68: CUST1269 | D68: PROD77 | E68: STORE2 | F68: 4 | G68: 814.25 | H68: 0.18 | I68: =F68*G68 -> 3257 | J68: =H68*(1-I68) -> -586.08 | K68: =TEXT(B68,"mmm") -> Sep | L68: =YEAR(B68) -> 2024 | N68: {=XLOOKUP(C68,Customer_Dim!A:A,Customer_Dim!B:B,"Not Found")} -> Tyrone Olson | O68: {=XLOOKUP(C68,Customer_Dim!A:A,Customer_Dim!E:E,"Not Found")} -> Emilytown | P68: {=XLOOKUP(D68,Product_Dim!A:A,Product_Dim!B:B,"Not Found")} -> WiFi Mesh Router | Q68: {=XLOOKUP(D68,Product_Dim!A:A,Product_Dim!C:C,"Not Found")} -> Electronics | R68: {=XLOOKUP(E68,Store_Dim!A:A,Store_Dim!B:B,"Not Found")} -> South | S68: {=XLOOKUP(E68,Store_Dim!A:A,Store_Dim!D:D,"Not Found")} -> Outlet
A69: SALE67 | B69: 45547 | C69: CUST1483 | D69: PROD12 | E69: STORE2 | F69: 1 | G69: 989.17 | H69: 0.2 | I69: =F69*G69 -> 989.17 | J69: =H69*(1-I69) -> -197.634 | K69: =TEXT(B69,"mmm") -> Sep | L69: =YEAR(B69) -> 2024 | N69: {=XLOOKUP(C69,Customer_Dim!A:A,Customer_Dim!B:B,"Not Found")} -> Sarah Smith | O69: {=XLOOKUP(C69,Customer_Dim!A:A,Customer_Dim!E:E,"Not Found")} -> East Rodney | P69: {=XLOOKUP(D69,Product_Dim!A:A,Product_Dim!B:B,"Not Found")} -> Hair Strengthening Shampoo | Q69: {=XLOOKUP(D69,Product_Dim!A:A,Product_Dim!C:C,"Not Found")} -> Beauty | R69: {=XLOOKUP(E69,Store_Dim!A:A,Store_Dim!B:B,"Not Found")} -> South | S69: {=XLOOKUP(E69,Store_Dim!A:A,Store_Dim!D:D,"Not Found")} -> Outlet
A70: SALE68 | B70: 45548 | C70: CUST1372 | D70: PROD72 | E70: STORE10 | F70: 4 | G70: 62.48 | H70: 0.18 | I70: =F70*G70 -> 249.92 | J70: =H70*(1-I70) -> -44.8056 | K70: =TEXT(B70,"mmm") -> Sep | L70: =YEAR(B70) -> 2024 | N70: {=XLOOKUP(C70,Customer_Dim!A:A,Customer_Dim!B:B,"Not Found")} -> Jacqueline Anthony | O70: {=XLOOKUP(C70,Customer_Dim!A:A,Customer_Dim!E:E,"Not Found")} -> Vincentside | P70: {=XLOOKUP(D70,Product_Dim!A:A,Product_Dim!B:B,"Not Found")} -> Professional Jump Rope | Q70: {=XLOOKUP(D70,Product_Dim!A:A,Product_Dim!C:C,"Not Found")} -> Sports | R70: {=XLOOKUP(E70,Store_Dim!A:A,Store_Dim!B:B,"Not Found")} -> East | S70: {=XLOOKUP(E70,Store_Dim!A:A,Store_Dim!D:D,"Not Found")} -> Online
A71: SALE69 | B71: 45549 | C71: CUST1423 | D71: PROD13 | E71: STORE16 | F71: 4 | G71: 561.24 | H71: 0.24 | I71: =F71*G71 -> 2244.96 | J71: =H71*(1-I71) -> -538.5504 | K71: =TEXT(B71,"mmm") -> Sep | L71: =YEAR(B71) -> 2024 | N71: {=XLOOKUP(C71,Customer_Dim!A:A,Customer_Dim!B:B,"Not Found")} -> Rebecca Baker | O71: {=XLOOKUP(C71,Customer_Dim!A:A,Customer_Dim!E:E,"Not Found")} -> New Katherine | P71: {=XLOOKUP(D71,Product_Dim!A:A,Product_Dim!B:B,"Not Found")} -> USB-C Fast Charger | Q71: {=XLOOKUP(D71,Product_Dim!A:A,Product_Dim!C:C,"Not Found")} -> Electronics | R71: {=XLOOKUP(E71,Store_Dim!A:A,Store_Dim!B:B,"Not Found")} -> West | S71: {=XLOOKUP(E71,Store_Dim!A:A,Store_Dim!D:D,"Not Found")} -> Flagship
A72: SALE70 | B72: 45550 | C72: CUST1058 | D72: PROD60 | E72: STORE5 | F72: 3 | G72: 92.24 | H72: 0.28 | I72: =F72*G72 -> 276.72 | J72: =H72*(1-I72) -> -77.2016 | K72: =TEXT(B72,"mmm") -> Sep | L72: =YEAR(B72) -> 2024 | N72: {=XLOOKUP(C72,Customer_Dim!A:A,Customer_Dim!B:B,"Not Found")} -> Cheryl Copeland | O72: {=XLOOKUP(C72,Customer_Dim!A:A,Customer_Dim!E:E,"Not Found")} -> Snowmouth | P72: {=XLOOKUP(D72,Product_Dim!A:A,Product_Dim!B:B,"Not Found")} -> Luxury Perfume Spray | Q72: {=XLOOKUP(D72,Product_Dim!A:A,Product_Dim!C:C,"Not Found")} -> Beauty | R72: {=XLOOKUP(E72,Store_Dim!A:A,Store_Dim!B:B,"Not Found")} -> North | S72: {=XLOOKUP(E72,Store_Dim!A:A,Store_Dim!D:D,"Not Found")} -> Outlet
... A260: SALE258 | B260: 45738 | C260: CUST1136 | D260: PROD35 | E260: STORE17 | F260: 1 | G260: 222.94 | H260: 0.19 | I260: =F260*G260 -> 222.94 | J260: =H260*(1-I260) -> -42.1686 | K260: =TEXT(B260,"mmm") -> Mar | L260: =YEAR(B260) -> 2025 | N260: {=XLOOKUP(C260,Customer_Dim!A:A,Customer_Dim!B:B,"Not Found")} -> Patrick Coleman | O260: {=XLOOKUP(C260,Customer_Dim!A:A,Customer_Dim!E:E,"Not Found")} -> New Jeffrey | P260: {=XLOOKUP(D260,Product_Dim!A:A,Product_Dim!B:B,"Not Found")} -> Bedroom Table Lamp | Q260: {=XLOOKUP(D260,Product_Dim!A:A,Product_Dim!C:C,"Not Found")} -> Home | R260: {=XLOOKUP(E260,Store_Dim!A:A,Store_Dim!B:B,"Not Found")} -> North | S260: {=XLOOKUP(E260,Store_Dim!A:A,Store_Dim!D:D,"Not Found")} -> Flagship
A261: SALE259 | B261: 45739 | C261: CUST1248 | D261: PROD35 | E261: STORE2 | F261: 2 | G261: 355.3 | I261: =F261*G261 -> 710.6 | J261: =H261*(1-I261) -> 0 | K261: =TEXT(B261,"mmm") -> Mar | L261: =YEAR(B261) -> 2025 | N261: {=XLOOKUP(C261,Customer_Dim!A:A,Customer_Dim!B:B,"Not Found")} -> Nicholas Webb | O261: {=XLOOKUP(C261,Customer_Dim!A:A,Customer_Dim!E:E,"Not Found")} -> Lake Timothy | P261: {=XLOOKUP(D261,Product_Dim!A:A,Product_Dim!B:B,"Not Found")} -> Bedroom Table Lamp | Q261: {=XLOOKUP(D261,Product_Dim!A:A,Product_Dim!C:C,"Not Found")} -> Home | R261: {=XLOOKUP(E261,Store_Dim!A:A,Store_Dim!B:B,"Not Found")} -> South | S261: {=XLOOKUP(E261,Store_Dim!A:A,Store_Dim!D:D,"Not Found")} -> Outlet
A262: SALE260 | B262: 45740 | C262: CUST1103 | D262: PROD89 | E262: STORE19 | F262: 4 | G262: 611.3 | H262: 0.11 | I262: =F262*G262 -> 2445.2 | J262: =H262*(1-I262) -> -268.862 | K262: =TEXT(B262,"mmm") -> Mar | L262: =YEAR(B262) -> 2025 | N262: {=XLOOKUP(C262,Customer_Dim!A:A,Customer_Dim!B:B,"Not Found")} -> Steven Stein | O262: {=XLOOKUP(C262,Customer_Dim!A:A,Customer_Dim!E:E,"Not Found")} -> West Lauren | P262: {=XLOOKUP(D262,Product_Dim!A:A,Product_Dim!B:B,"Not Found")} -> Face Foundation Kit | Q262: {=XLOOKUP(D262,Product_Dim!A:A,Product_Dim!C:C,"Not Found")} -> Beauty | R262: {=XLOOKUP(E262,Store_Dim!A:A,Store_Dim!B:B,"Not Found")} -> East | S262: {=XLOOKUP(E262,Store_Dim!A:A,Store_Dim!D:D,"Not Found")} -> Online
A263: SALE261 | B263: 45741 | C263: CUST1333 | D263: PROD0 | E263: STORE8 | F263: 4 | G263: 849.21 | H263: 0.07 | I263: =F263*G263 -> 3396.84 | J263: =H263*(1-I263) -> -237.7088 | K263: =TEXT(B263,"mmm") -> Mar | L263: =YEAR(B263) -> 2025 | N263: {=XLOOKUP(C263,Customer_Dim!A:A,Customer_Dim!B:B,"Not Found")} -> Teresa Johnson | O263: {=XLOOKUP(C263,Customer_Dim!A:A,Customer_Dim!E:E,"Not Found")} -> Johnsonbury | P263: {=XLOOKUP(D263,Product_Dim!A:A,Product_Dim!B:B,"Not Found")} -> Brother Laser Printer | Q263: {=XLOOKUP(D263,Product_Dim!A:A,Product_Dim!C:C,"Not Found")} -> Electronics | R263: {=XLOOKUP(E263,Store_Dim!A:A,Store_Dim!B:B,"Not Found")} -> West | S263: {=XLOOKUP(E263,Store_Dim!A:A,Store_Dim!D:D,"Not Found")} -> Online
A264: SALE262 | B264: 45742 | C264: CUST1209 | D264: PROD42 | E264: STORE7 | F264: 3 | G264: 553.12 | H264: 0.28 | I264: =F264*G264 -> 1659.36 | J264: =H264*(1-I264) -> -464.3408 | K264: =TEXT(B264,"mmm") -> Mar | L264: =YEAR(B264) -> 2025 | N264: {=XLOOKUP(C264,Customer_Dim!A:A,Customer_Dim!B:B,"Not Found")} -> Joan Johnson | O264: {=XLOOKUP(C264,Customer_Dim!A:A,Customer_Dim!E:E,"Not Found")} -> Lake Josephport | P264: {=XLOOKUP(D264,Product_Dim!A:A,Product_Dim!B:B,"Not Found")} -> Smart Home WiFi Camera | Q264: {=XLOOKUP(D264,Product_Dim!A:A,Product_Dim!C:C,"Not Found")} -> Electronics | R264: {=XLOOKUP(E264,Store_Dim!A:A,Store_Dim!B:B,"Not Found")} -> South | S264: {=XLOOKUP(E264,Store_Dim!A:A,Store_Dim!D:D,"Not Found")} -> Online
A265: SALE263 | B265: 45743 | C265: CUST1282 | D265: PROD91 | E265: STORE9 | F265: 2 | G265: 903.08 | H265: 0.18 | I265: =F265*G265 -> 1806.16 | J265: =H265*(1-I265) -> -324.9288 | K265: =TEXT(B265,"mmm") -> Mar | L265: =YEAR(B265) -> 2025 | N265: {=XLOOKUP(C265,Customer_Dim!A:A,Customer_Dim!B:B,"Not Found")} -> Kristi Lopez | O265: {=XLOOKUP(C265,Customer_Dim!A:A,Customer_Dim!E:E,"Not Found")} -> Spencermouth | P265: {=XLOOKUP(D265,Product_Dim!A:A,Product_Dim!B:B,"Not Found")} -> Women's High Heels | Q265: {=XLOOKUP(D265,Product_Dim!A:A,Product_Dim!C:C,"Not Found")} -> Clothing | R265: {=XLOOKUP(E265,Store_Dim!A:A,Store_Dim!B:B,"Not Found")} -> South | S265: {=XLOOKUP(E265,Store_Dim!A:A,Store_Dim!D:D,"Not Found")} -> Flagship
A266: SALE264 | B266: 45744 | C266: CUST1478 | D266: PROD16 | E266: STORE11 | F266: 4 | G266: 640.23 | H266: 0.06 | I266: =F266*G266 -> 2560.92 | J266: =H266*(1-I266) -> -153.5952 | K266: =TEXT(B266,"mmm") -> Mar | L266: =YEAR(B266) -> 2025 | N266: {=XLOOKUP(C266,Customer_Dim!A:A,Customer_Dim!B:B,"Not Found")} -> Earl Smith DDS | O266: {=XLOOKUP(C266,Customer_Dim!A:A,Customer_Dim!E:E,"Not Found")} -> West Sarah | P266: {=XLOOKUP(D266,Product_Dim!A:A,Product_Dim!B:B,"Not Found")} -> Not Found | Q266: {=XLOOKUP(D266,Product_Dim!A:A,Product_Dim!C:C,"Not Found")} -> Not Found | R266: {=XLOOKUP(E266,Store_Dim!A:A,Store_Dim!B:B,"Not Found")} -> South | S266: {=XLOOKUP(E266,Store_Dim!A:A,Store_Dim!D:D,"Not Found")} -> Online
A267: SALE265 | B267: 45745 | C267: CUST1141 | D267: PROD21 | E267: STORE6 | F267: 1 | G267: 518 | H267: 0.25 | I267: =F267*G267 -> 518 | J267: =H267*(1-I267) -> -129.25 | K267: =TEXT(B267,"mmm") -> Mar | L267: =YEAR(B267) -> 2025 | N267: {=XLOOKUP(C267,Customer_Dim!A:A,Customer_Dim!B:B,"Not Found")} -> Cristian Wright | O267: {=XLOOKUP(C267,Customer_Dim!A:A,Customer_Dim!E:E,"Not Found")} -> Port Denise | P267: {=XLOOKUP(D267,Product_Dim!A:A,Product_Dim!B:B,"Not Found")} -> Multi-Purpose Storage Box | Q267: {=XLOOKUP(D267,Product_Dim!A:A,Product_Dim!C:C,"Not Found")} -> Home | R267: {=XLOOKUP(E267,Store_Dim!A:A,Store_Dim!B:B,"Not Found")} -> East | S267: {=XLOOKUP(E267,Store_Dim!A:A,Store_Dim!D:D,"Not Found")} -> Online
A268: SALE266 | B268: 45746 | C268: CUST1433 | D268: PROD64 | E268: STORE4 | F268: 4 | G268: 779.25 | H268: 0.25 | I268: =F268*G268 -> 3117 | J268: =H268*(1-I268) -> -779 | K268: =TEXT(B268,"mmm") -> Mar | L268: =YEAR(B268) -> 2025 | N268: {=XLOOKUP(C268,Customer_Dim!A:A,Customer_Dim!B:B,"Not Found")} -> Thomas Moore | O268: {=XLOOKUP(C268,Customer_Dim!A:A,Customer_Dim!E:E,"Not Found")} -> Williamsberg | P268: {=XLOOKUP(D268,Product_Dim!A:A,Product_Dim!B:B,"Not Found")} -> Matte Lipstick Set | Q268: {=XLOOKUP(D268,Product_Dim!A:A,Product_Dim!C:C,"Not Found")} -> Beauty | R268: {=XLOOKUP(E268,Store_Dim!A:A,Store_Dim!B:B,"Not Found")} -> South | S268: {=XLOOKUP(E268,Store_Dim!A:A,Store_Dim!D:D,"Not Found")} -> Online
A269: SALE267 | B269: 45747 | C269: CUST1118 | D269: PROD83 | E269: STORE7 | F269: 2 | G269: 467.75 | H269: 0.26 | I269: =F269*G269 -> 935.5 | J269: =H269*(1-I269) -> -242.97 | K269: =TEXT(B269,"mmm") -> Mar | L269: =YEAR(B269) -> 2025 | N269: {=XLOOKUP(C269,Customer_Dim!A:A,Customer_Dim!B:B,"Not Found")} -> Earl Allen | O269: {=XLOOKUP(C269,Customer_Dim!A:A,Customer_Dim!E:E,"Not Found")} -> New Jenniferburgh | P269: {=XLOOKUP(D269,Product_Dim!A:A,Product_Dim!B:B,"Not Found")} -> Hydrating Face Cleanser | Q269: {=XLOOKUP(D269,Product_Dim!A:A,Product_Dim!C:C,"Not Found")} -> Beauty | R269: {=XLOOKUP(E269,Store_Dim!A:A,Store_Dim!B:B,"Not Found")} -> South | S269: {=XLOOKUP(E269,Store_Dim!A:A,Store_Dim!D:D,"Not Found")} -> Online
A270: SALE268 | B270: 45748 | C270: CUST1406 | D270: PROD90 | E270: STORE18 | F270: 3 | H270: 0.06 | I270: =F270*G270 -> 0 | J270: =H270*(1-I270) -> 0.06 | K270: =TEXT(B270,"mmm") -> Apr | L270: =YEAR(B270) -> 2025 | N270: {=XLOOKUP(C270,Customer_Dim!A:A,Customer_Dim!B:B,"Not Found")} -> David Lozano | O270: {=XLOOKUP(C270,Customer_Dim!A:A,Customer_Dim!E:E,"Not Found")} -> North Michaelfurt | P270: {=XLOOKUP(D270,Product_Dim!A:A,Product_Dim!B:B,"Not Found")} -> Gaming Mouse Pad XL | Q270: {=XLOOKUP(D270,Product_Dim!A:A,Product_Dim!C:C,"Not Found")} -> Electronics | R270: {=XLOOKUP(E270,Store_Dim!A:A,Store_Dim!B:B,"Not Found")} -> East | S270: {=XLOOKUP(E270,Store_Dim!A:A,Store_Dim!D:D,"Not Found")} -> Flagship
A271: SALE269 | B271: 45749 | C271: CUST1219 | D271: PROD37 | E271: STORE0 | F271: 4 | G271: 747.01 | H271: 0.13 | I271: =F271*G271 -> 2988.04 | J271: =H271*(1-I271) -> -388.3152 | K271: =TEXT(B271,"mmm") -> Apr | L271: =YEAR(B271) -> 2025 | N271: {=XLOOKUP(C271,Customer_Dim!A:A,Customer_Dim!B:B,"Not Found")} -> Jordan Wells | O271: {=XLOOKUP(C271,Customer_Dim!A:A,Customer_Dim!E:E,"Not Found")} -> Phillipschester | P271: {=XLOOKUP(D271,Product_Dim!A:A,Product_Dim!B:B,"Not Found")} -> Men's Casual Sneakers | Q271: {=XLOOKUP(D271,Product_Dim!A:A,Product_Dim!C:C,"Not Found")} -> Clothing | R271: {=XLOOKUP(E271,Store_Dim!A:A,Store_Dim!B:B,"Not Found")} -> East | S271: {=XLOOKUP(E271,Store_Dim!A:A,Store_Dim!D:D,"Not Found")} -> Flagship
A272: SALE270 | B272: 45750 | C272: CUST1101 | D272: PROD89 | E272: STORE12 | F272: 4 | G272: 461.83 | H272: 0.28 | I272: =F272*G272 -> 1847.32 | J272: =H272*(1-I272) -> -516.9696 | K272: =TEXT(B272,"mmm") -> Apr | L272: =YEAR(B272) -> 2025 | N272: {=XLOOKUP(C272,Customer_Dim!A:A,Customer_Dim!B:B,"Not Found")} -> Colleen Maynard | O272: {=XLOOKUP(C272,Customer_Dim!A:A,Customer_Dim!E:E,"Not Found")} -> Singletonmouth | P272: {=XLOOKUP(D272,Product_Dim!A:A,Product_Dim!B:B,"Not Found")} -> Face Foundation Kit | Q272: {=XLOOKUP(D272,Product_Dim!A:A,Product_Dim!C:C,"Not Found")} -> Beauty | R272: {=XLOOKUP(E272,Store_Dim!A:A,Store_Dim!B:B,"Not Found")} -> North | S272: {=XLOOKUP(E272,Store_Dim!A:A,Store_Dim!D:D,"Not Found")} -> Online
A273: SALE271 | B273: 45751 | C273: CUST1134 | D273: PROD70 | E273: STORE8 | F273: 2 | G273: 105.15 | H273: 0.06 | I273: =F273*G273 -> 210.3 | J273: =H273*(1-I273) -> -12.558 | K273: =TEXT(B273,"mmm") -> Apr | L273: =YEAR(B273) -> 2025 | N273: {=XLOOKUP(C273,Customer_Dim!A:A,Customer_Dim!B:B,"Not Found")} -> Morgan Bowen | O273: {=XLOOKUP(C273,Customer_Dim!A:A,Customer_Dim!E:E,"Not Found")} -> Parksfort | P273: {=XLOOKUP(D273,Product_Dim!A:A,Product_Dim!B:B,"Not Found")} -> Kitchen Storage Rack | Q273: {=XLOOKUP(D273,Product_Dim!A:A,Product_Dim!C:C,"Not Found")} -> Home | R273: {=XLOOKUP(E273,Store_Dim!A:A,Store_Dim!B:B,"Not Found")} -> West | S273: {=XLOOKUP(E273,Store_Dim!A:A,Store_Dim!D:D,"Not Found")} -> Online
A274: SALE272 | B274: 45752 | C274: CUST1033 | D274: PROD23 | E274: STORE3 | F274: 3 | G274: 610.24 | H274: 0.17 | I274: =F274*G274 -> 1830.72 | J274: =H274*(1-I274) -> -311.0524 | K274: =TEXT(B274,"mmm") -> Apr | L274: =YEAR(B274) -> 2025 | N274: {=XLOOKUP(C274,Customer_Dim!A:A,Customer_Dim!B:B,"Not Found")} -> Robert Jones DDS | O274: {=XLOOKUP(C274,Customer_Dim!A:A,Customer_Dim!E:E,"Not Found")} -> Tristanton | P274: {=XLOOKUP(D274,Product_Dim!A:A,Product_Dim!B:B,"Not Found")} -> Men's Formal Shirt | Q274: {=XLOOKUP(D274,Product_Dim!A:A,Product_Dim!C:C,"Not Found")} -> Clothing | R274: {=XLOOKUP(E274,Store_Dim!A:A,Store_Dim!B:B,"Not Found")} -> North | S274: {=XLOOKUP(E274,Store_Dim!A:A,Store_Dim!D:D,"Not Found")} -> Outlet
A275: SALE273 | B275: 45753 | C275: CUST1312 | D275: PROD74 | E275: STORE8 | F275: 1 | G275: 872.12 | H275: 0.07 | I275: =F275*G275 -> 872.12 | J275: =H275*(1-I275) -> -60.9784 | K275: =TEXT(B275,"mmm") -> Apr | L275: =YEAR(B275) -> 2025 | N275: {=XLOOKUP(C275,Customer_Dim!A:A,Customer_Dim!B:B,"Not Found")} -> Jason Mullins | O275: {=XLOOKUP(C275,Customer_Dim!A:A,Customer_Dim!E:E,"Not Found")} -> Brianchester | P275: {=XLOOKUP(D275,Product_Dim!A:A,Product_Dim!B:B,"Not Found")} -> Bluetooth Car Audio System | Q275: {=XLOOKUP(D275,Product_Dim!A:A,Product_Dim!C:C,"Not Found")} -> Electronics | R275: {=XLOOKUP(E275,Store_Dim!A:A,Store_Dim!B:B,"Not Found")} -> West | S275: {=XLOOKUP(E275,Store_Dim!A:A,Store_Dim!D:D,"Not Found")} -> Online
A276: SALE274 | B276: 45754 | C276: CUST1433 | D276: PROD10 | E276: STORE1 | F276: 1 | G276: 406.79 | H276: 0.03 | I276: =F276*G276 -> 406.79 | J276: =H276*(1-I276) -> -12.1737 | K276: =TEXT(B276,"mmm") -> Apr | L276: =YEAR(B276) -> 2025 | N276: {=XLOOKUP(C276,Customer_Dim!A:A,Customer_Dim!B:B,"Not Found")} -> Thomas Moore | O276: {=XLOOKUP(C276,Customer_Dim!A:A,Customer_Dim!E:E,"Not Found")} -> Williamsberg | P276: {=XLOOKUP(D276,Product_Dim!A:A,Product_Dim!B:B,"Not Found")} -> Ceramic Kitchen Bowl Set | Q276: {=XLOOKUP(D276,Product_Dim!A:A,Product_Dim!C:C,"Not Found")} -> Home | R276: {=XLOOKUP(E276,Store_Dim!A:A,Store_Dim!B:B,"Not Found")} -> North | S276: {=XLOOKUP(E276,Store_Dim!A:A,Store_Dim!D:D,"Not Found")} -> Flagship
A277: SALE275 | B277: 45755 | C277: CUST1372 | D277: PROD54 | E277: STORE14 | F277: 1 | G277: 606.01 | H277: 0.04 | I277: =F277*G277 -> 606.01 | J277: =H277*(1-I277) -> -24.2004 | K277: =TEXT(B277,"mmm") -> Apr | L277: =YEAR(B277) -> 2025 | N277: {=XLOOKUP(C277,Customer_Dim!A:A,Customer_Dim!B:B,"Not Found")} -> Jacqueline Anthony | O277: {=XLOOKUP(C277,Customer_Dim!A:A,Customer_Dim!E:E,"Not Found")} -> Vincentside | P277: {=XLOOKUP(D277,Product_Dim!A:A,Product_Dim!B:B,"Not Found")} -> Sports Stopwatch Pro | Q277: {=XLOOKUP(D277,Product_Dim!A:A,Product_Dim!C:C,"Not Found")} -> Sports | R277: {=XLOOKUP(E277,Store_Dim!A:A,Store_Dim!B:B,"Not Found")} -> South | S277: {=XLOOKUP(E277,Store_Dim!A:A,Store_Dim!D:D,"Not Found")} -> Outlet
A278: SALE276 | B278: 45756 | C278: CUST1349 | D278: PROD17 | E278: STORE5 | F278: 4 | G278: 322.58 | H278: 0.06 | I278: =F278*G278 -> 1290.32 | J278: =H278*(1-I278) -> -77.3592 | K278: =TEXT(B278,"mmm") -> Apr | L278: =YEAR(B278) -> 2025 | N278: {=XLOOKUP(C278,Customer_Dim!A:A,Customer_Dim!B:B,"Not Found")} -> Heather Valenzuela | O278: {=XLOOKUP(C278,Customer_Dim!A:A,Customer_Dim!E:E,"Not Found")} -> New Angiefurt | P278: {=XLOOKUP(D278,Product_Dim!A:A,Product_Dim!B:B,"Not Found")} -> Soccer Training Cone Set | Q278: {=XLOOKUP(D278,Product_Dim!A:A,Product_Dim!C:C,"Not Found")} -> Sports | R278: {=XLOOKUP(E278,Store_Dim!A:A,Store_Dim!B:B,"Not Found")} -> North | S278: {=XLOOKUP(E278,Store_Dim!A:A,Store_Dim!D:D,"Not Found")} -> Outlet
A279: SALE277 | B279: 45757 | C279: CUST1484 | D279: PROD77 | E279: STORE18 | F279: 4 | G279: 463.17 | H279: 0.06 | I279: =F279*G279 -> 1852.68 | J279: =H279*(1-I279) -> -111.1008 | K279: =TEXT(B279,"mmm") -> Apr | L279: =YEAR(B279) -> 2025 | N279: {=XLOOKUP(C279,Customer_Dim!A:A,Customer_Dim!B:B,"Not Found")} -> Jessica Castro | O279: {=XLOOKUP(C279,Customer_Dim!A:A,Customer_Dim!E:E,"Not Found")} -> West Markton | P279: {=XLOOKUP(D279,Product_Dim!A:A,Product_Dim!B:B,"Not Found")} -> WiFi Mesh Router | Q279: {=XLOOKUP(D279,Product_Dim!A:A,Product_Dim!C:C,"Not Found")} -> Electronics | R279: {=XLOOKUP(E279,Store_Dim!A:A,Store_Dim!B:B,"Not Found")} -> East | S279: {=XLOOKUP(E279,Store_Dim!A:A,Store_Dim!D:D,"Not Found")} -> Flagship
A280: SALE278 | B280: 45758 | C280: CUST1316 | D280: PROD25 | E280: STORE7 | F280: 4 | G280: 285.82 | H280: 0.18 | I280: =F280*G280 -> 1143.28 | J280: =H280*(1-I280) -> -205.6104 | K280: =TEXT(B280,"mmm") -> Apr | L280: =YEAR(B280) -> 2025 | N280: {=XLOOKUP(C280,Customer_Dim!A:A,Customer_Dim!B:B,"Not Found")} -> Robert House | O280: {=XLOOKUP(C280,Customer_Dim!A:A,Customer_Dim!E:E,"Not Found")} -> Lake James | P280: {=XLOOKUP(D280,Product_Dim!A:A,Product_Dim!B:B,"Not Found")} -> Women's Scarf Set | Q280: {=XLOOKUP(D280,Product_Dim!A:A,Product_Dim!C:C,"Not Found")} -> Clothing | R280: {=XLOOKUP(E280,Store_Dim!A:A,Store_Dim!B:B,"Not Found")} -> South | S280: {=XLOOKUP(E280,Store_Dim!A:A,Store_Dim!D:D,"Not Found")} -> Online
A281: SALE279 | B281: 45759 | C281: CUST1326 | D281: PROD37 | E281: STORE11 | F281: 3 | G281: 995.38 | H281: 0.1 | I281: =F281*G281 -> 2986.14 | J281: =H281*(1-I281) -> -298.514 | K281: =TEXT(B281,"mmm") -> Apr | L281: =YEAR(B281) -> 2025 | N281: {=XLOOKUP(C281,Customer_Dim!A:A,Customer_Dim!B:B,"Not Found")} -> Robert King | O281: {=XLOOKUP(C281,Customer_Dim!A:A,Customer_Dim!E:E,"Not Found")} -> Cindyton | P281: {=XLOOKUP(D281,Product_Dim!A:A,Product_Dim!B:B,"Not Found")} -> Men's Casual Sneakers | Q281: {=XLOOKUP(D281,Product_Dim!A:A,Product_Dim!C:C,"Not Found")} -> Clothing | R281: {=XLOOKUP(E281,Store_Dim!A:A,Store_Dim!B:B,"Not Found")} -> South | S281: {=XLOOKUP(E281,Store_Dim!A:A,Store_Dim!D:D,"Not Found")} -> Online
A282: SALE280 | B282: 45760 | C282: CUST1119 | D282: PROD62 | E282: STORE8 | F282: 1 | G282: 329.31 | H282: 0.09 | I282: =F282*G282 -> 329.31 | J282: =H282*(1-I282) -> -29.5479 | K282: =TEXT(B282,"mmm") -> Apr | L282: =YEAR(B282) -> 2025 | N282: {=XLOOKUP(C282,Customer_Dim!A:A,Customer_Dim!B:B,"Not Found")} -> Michael Jones | O282: {=XLOOKUP(C282,Customer_Dim!A:A,Customer_Dim!E:E,"Not Found")} -> North Edwardton | P282: {=XLOOKUP(D282,Product_Dim!A:A,Product_Dim!B:B,"Not Found")} -> Laptop Cooling Pad | Q282: {=XLOOKUP(D282,Product_Dim!A:A,Product_Dim!C:C,"Not Found")} -> Electronics | R282: {=XLOOKUP(E282,Store_Dim!A:A,Store_Dim!B:B,"Not Found")} -> West | S282: {=XLOOKUP(E282,Store_Dim!A:A,Store_Dim!D:D,"Not Found")} -> Online
... A2001: SALE1999 | B2001: 47479 | C2001: CUST1023 | D2001: PROD76 | E2001: STORE19 | F2001: 3 | G2001: 68.45 | H2001: 0.17 | I2001: =F2001*G2001 -> 205.35 | J2001: =H2001*(1-I2001) -> -34.7395 | K2001: =TEXT(B2001,"mmm") -> Dec | L2001: =YEAR(B2001) -> 2029 | N2001: {=XLOOKUP(C2001,Customer_Dim!A:A,Customer_Dim!B:B,"Not Found")} -> Jonathan Steele | O2001: {=XLOOKUP(C2001,Customer_Dim!A:A,Customer_Dim!E:E,"Not Found")} -> Molinabury | P2001: {=XLOOKUP(D2001,Product_Dim!A:A,Product_Dim!B:B,"Not Found")} -> Wireless Mouse | Q2001: {=XLOOKUP(D2001,Product_Dim!A:A,Product_Dim!C:C,"Not Found")} -> Electronics | R2001: {=XLOOKUP(E2001,Store_Dim!A:A,Store_Dim!B:B,"Not Found")} -> East | S2001: {=XLOOKUP(E2001,Store_Dim!A:A,Store_Dim!D:D,"Not Found")} -> Online

Sheet CUSTOMER_PIVOT_TABLE

Sheet STORE_PIVOT_TABLE
